PE64_with MUX (180nm)/Code Files/priority_mux.v
`timescale 1ns / 1ps
// ====================================================================
// Standard 4-bit Priority Encoder (PE4)
// (Base module, no changes needed)
// ====================================================================
module pe4 (
    input  wire [3:0] d,
    output wire [1:0] q,
    output wire       v
);
    assign q[1] = d[3] | d[2];
    assign q[0] = d[3] | (d[1] & ~d[2]);
    assign v = |d;
endmodule

// ====================================================================
// 16-bit Priority Encoder (PE16)
// (Replaced 'case' block with a 4:1 MUX)
// ====================================================================
module pe16 (
    input  wire [15:0] d,
    output wire [3:0]  q,
    output wire        v
);
    wire [3:0] row_status;
    wire [1:0] row_index;
    wire [1:0] col_index;
    wire       row_valid;
    wire [3:0] selected_row; // Changed from reg to wire

    assign row_status[0] = |d[3:0];
    assign row_status[1] = |d[7:4];
    assign row_status[2] = |d[11:8];
    assign row_status[3] = |d[15:12];

    pe4 row_pe (
        .d(row_status),
        .q(row_index),
        .v(row_valid)
    );

    // MUX-based selection for selected_row (4:1 MUX, 4-bits wide)
    // S[1:0] = row_index
    // I0 = d[3:0], I1 = d[7:4], I2 = d[11:8], I3 = d[15:12]
    assign selected_row = (row_index == 2'b00) ? d[3:0]    :
                          (row_index == 2'b01) ? d[7:4]    :
                          (row_index == 2'b10) ? d[11:8]   :
                          (row_index == 2'b11) ? d[15:12]  : 4'b0000; // Default case

    pe4 col_pe (
        .d(selected_row),
        .q(col_index),
        .v() // valid bit is not needed here
    );

    assign q = {row_index, col_index};
    assign v = row_valid;
endmodule

// ====================================================================
// 64-bit Priority Encoder (PE64_standard)
// (Replaced 16-input 'case' with a two-stage 4:1 MUX tree)
// ====================================================================
module pe64_standard (
    input  wire [63:0] d,
    output wire [5:0]  q,
    output wire        v
);
    wire [15:0] row_status;
    wire [3:0]  selected_row; // Changed from reg to wire
    wire [3:0]  row_index;
    wire [1:0]  col_index;
    wire        row_valid;

    genvar i;
    generate
        for (i = 0; i < 16; i = i + 1) begin : row_logic
            assign row_status[i] = |d[(i*4)+3 : i*4];
        end
    endgenerate

    pe16 row_pe (
        .d(row_status),
        .q(row_index),
        .v(row_valid)
    );

    // 16:1 MUX for selected_row using two stages of 4:1 MUXes (4 bits wide each)
    wire [3:0] mux_stage1_out0; // Group 0: d[15:0] selected by row_index[1:0]
    wire [3:0] mux_stage1_out1; // Group 1: d[31:16] selected by row_index[1:0]
    wire [3:0] mux_stage1_out2; // Group 2: d[47:32] selected by row_index[1:0]
    wire [3:0] mux_stage1_out3; // Group 3: d[63:48] selected by row_index[1:0]

    // --- Stage 1 MUXes (Select lines S[1:0] = row_index[1:0]) ---
    // MUX 0
    assign mux_stage1_out0 = (row_index[1:0] == 2'b00) ? d[3:0]    :
                             (row_index[1:0] == 2'b01) ? d[7:4]    :
                             (row_index[1:0] == 2'b10) ? d[11:8]   : d[15:12];
    // MUX 1
    assign mux_stage1_out1 = (row_index[1:0] == 2'b00) ? d[19:16]  :
                             (row_index[1:0] == 2'b01) ? d[23:20]  :
                             (row_index[1:0] == 2'b10) ? d[27:24]  : d[31:28];
    // MUX 2
    assign mux_stage1_out2 = (row_index[1:0] == 2'b00) ? d[35:32]  :
                             (row_index[1:0] == 2'b01) ? d[39:36]  :
                             (row_index[1:0] == 2'b10) ? d[43:40]  : d[47:44];
    // MUX 3
    assign mux_stage1_out3 = (row_index[1:0] == 2'b00) ? d[51:48]  :
                             (row_index[1:0] == 2'b01) ? d[55:52]  :
                             (row_index[1:0] == 2'b10) ? d[59:56]  : d[63:60];

    // --- Stage 2 MUX (Select lines S[1:0] = row_index[3:2]) ---
    assign selected_row = (row_index[3:2] == 2'b00) ? mux_stage1_out0 :
                          (row_index[3:2] == 2'b01) ? mux_stage1_out1 :
                          (row_index[3:2] == 2'b10) ? mux_stage1_out2 :
                          (row_index[3:2] == 2'b11) ? mux_stage1_out3 : 4'b0000;

    pe4 col_pe (
        .d(selected_row),
        .q(col_index),
        .v()
    );

    assign q = {row_index, col_index};
    assign v = row_valid;
endmodule

// ====================================================================
// 64-bit Priority Encoder (PE64_lookahead)
// (Replaced 'casex' with a 16:1 MUX tree selected by row_index)
// ====================================================================
module pe64_lookahead (
    input  wire [63:0] d,
    output wire [5:0]  q,
    output wire        v
);
    wire [15:0] dor;
    wire [3:0]  row_index;
    wire [3:0]  column_data; // Changed from reg+wire to single wire
    wire [1:0]  col_index;
    wire        row_valid;

    genvar i;
    generate
        for (i = 0; i < 16; i = i + 1) begin : row_or_logic
            assign dor[i] = |d[(i*4)+3 : i*4];
        end
    endgenerate

    pe16 row_encoder (
        .d(dor),
        .q(row_index),
        .v(row_valid)
    );

    // The 'casex' block is replaced by a standard 16:1 MUX (as a 4:1 MUX tree)
    // that uses the pre-computed 'row_index' as its select signal.
    // This maintains the original priority logic, which is now fully
    // encapsulated within the 'pe16 row_encoder'.

    wire [3:0] mux_stage1_out0;
    wire [3:0] mux_stage1_out1;
    wire [3:0] mux_stage1_out2;
    wire [3:0] mux_stage1_out3;

    // --- Stage 1 MUXes (Select lines S[1:0] = row_index[1:0]) ---
    assign mux_stage1_out0 = (row_index[1:0] == 2'b00) ? d[3:0]    :
                             (row_index[1:0] == 2'b01) ? d[7:4]    :
                             (row_index[1:0] == 2'b10) ? d[11:8]   : d[15:12];

    assign mux_stage1_out1 = (row_index[1:0] == 2'b00) ? d[19:16]  :
                             (row_index[1:0] == 2'b01) ? d[23:20]  :
                             (row_index[1:0] == 2'b10) ? d[27:24]  : d[31:28];

    assign mux_stage1_out2 = (row_index[1:0] == 2'b00) ? d[35:32]  :
                             (row_index[1:0] == 2'b01) ? d[39:36]  :
                             (row_index[1:0] == 2'b10) ? d[43:40]  : d[47:44];

    assign mux_stage1_out3 = (row_index[1:0] == 2'b00) ? d[51:48]  :
                             (row_index[1:0] == 2'b01) ? d[55:52]  :
                             (row_index[1:0] == 2'b10) ? d[59:56]  : d[63:60];

    // --- Stage 2 MUX (Select lines S[1:0] = row_index[3:2]) ---
    assign column_data = (row_index[3:2] == 2'b00) ? mux_stage1_out0 :
                         (row_index[3:2] == 2'b01) ? mux_stage1_out1 :
                         (row_index[3:2] == 2'b10) ? mux_stage1_out2 :
                         (row_index[3:2] == 2'b11) ? mux_stage1_out3 : 4'b0000;

    pe4 col_encoder (
        .d(column_data),
        .q(col_index),
        .v()
    );

    assign q = {row_index, col_index};
    assign v = row_valid;
endmodule

// ====================================================================
// 256-bit Priority Encoder (PE256_scalable)
// (Original code already uses the 4:1 MUX conditional operator)
// ====================================================================
module pe256_scalable (
    input  wire [255:0] d,
    output wire [7:0]   q,
    output wire         v
);
    wire [3:0] block_status;
    wire [1:0] block_index;
    wire [5:0] internal_index;
    wire       block_valid, internal_valid;

    assign block_status[0] = |d[63:0];
    assign block_status[1] = |d[127:64];
    assign block_status[2] = |d[191:128];
    assign block_status[3] = |d[255:192];

    pe4 block_selector (
        .d(block_status),
        .q(block_index),
        .v(block_valid)
    );

    // This is the 4:1 MUX (64-bits wide) for block selection.
    // This structure is correct for synthesis.
    wire [63:0] selected_block;
    assign selected_block = (block_index == 2'b00) ? d[63:0]     :
                            (block_index == 2'b01) ? d[127:64]   :
                            (block_index == 2'b10) ? d[191:128]  :
                            (block_index == 2'b11) ? d[255:192]  : 64'b0;

    pe64_lookahead internal_pe (
        .d(selected_block),
        .q(internal_index),
        .v(internal_valid)
    );

    assign q = {block_index, internal_index};
    assign v = block_valid;
endmodule

PE64_with MUX (180nm)/Code Files/priority_mux_tb.v
`timescale 1ns / 1ps
`include "priority_mux.v"

module tb_pe256_scalable_selfchecking();

    reg  [255:0] tb_d;
    wire [7:0]   tb_q;
    wire         tb_v;

    integer error_count;
    reg [7:0] expected_q;
    integer i;

    pe256_scalable dut (
        .d(tb_d),
        .q(tb_q),
        .v(tb_v)
    );

    // CORRECTED FUNCTION FOR VERILOG-2001
    function [7:0] get_expected_q(input [255:0] d);
        integer i;
        begin : find_bit_block // Named block for disable
            get_expected_q = 8'b0; // Default value if no bit is set
            for (i = 255; i >= 0; i = i - 1) begin
                if (d[i] == 1'b1) begin
                    get_expected_q = i; // Assign return value to function name
                    disable find_bit_block; // Exit the loop and function
                end
            end
        end
    endfunction

    initial begin
        $dumpfile("pe256.vcd");
        $dumpvars(0, tb_pe256_scalable_selfchecking);
        error_count = 0;
        
        tb_d = 256'b0;
        #10;
        if (tb_v !== 1'b0) begin
            $display("FAIL: All-zero input, but valid signal is high.");
            error_count = error_count + 1;
        end

        for (i = 0; i < 256; i = i + 1) begin
            tb_d = 0;
            tb_d[i] = 1'b1;
            expected_q = i;
            #10;
            if (tb_q !== expected_q || tb_v !== 1'b1) begin
                $display("FAIL: Input bit %0d | Expected: %0d | Got: %0d", i, expected_q, tb_q);
                error_count = error_count + 1;
            end
        end

        tb_d = 0;
        tb_d[123] = 1'b1;
        tb_d[200] = 1'b1;
        tb_d[5]   = 1'b1;
        expected_q = 200;
        #10;
        if (tb_q !== expected_q) begin
            $display("FAIL: Multi-bit test | Expected: %0d | Got: %0d", expected_q, tb_q);
            error_count = error_count + 1;
        end

        for (i = 0; i < 20; i = i + 1) begin
            tb_d = {$random, $random, $random, $random, $random, $random, $random, $random};
            expected_q = get_expected_q(tb_d);
            #10;
            if (tb_q !== expected_q) begin
                $display("FAIL: Random test | Input: %h | Expected: %0d | Got: %0d", tb_d, expected_q, tb_q);
                error_count = error_count + 1;
            end
        end

        #20;
        if (error_count == 0) begin
            $display("SUCCESS: All tests passed!");
        end else begin
            $display("FAILURE: %0d errors found.", error_count);
        end

        $finish;
    end

endmodule

PE64_with MUX (180nm)/Code Files/pe256.vcd
$date
    Oct 31, 2025  14:48:49
$end
$version
    TOOL:	ncsim(64)	15.20-s086
$end
$timescale
    1 ps
$end

$scope module tb_pe256_scalable_selfchecking $end
$var reg      256 !    tb_d [255:0] $end
$var wire      8 "    tb_q [7:0] $end
$var wire      1 #    tb_v  $end
$var integer  32 $    error_count  $end
$var reg       8 %    expected_q [7:0] $end
$var integer  32 &    i  $end

$scope module dut $end
$var wire     256 '    d [255:0] $end
$var wire      8 "    q [7:0] $end
$var wire      1 #    v  $end
$var wire      1 (    block_status [3] $end
$var wire      1 )    block_status [2] $end
$var wire      1 *    block_status [1] $end
$var wire      1 +    block_status [0] $end
$var wire      1 ,    block_index [1] $end
$var wire      1 -    block_index [0] $end
$var wire      6 .    internal_index [5:0] $end
$var wire      1 /    block_valid  $end
$var wire      1 0    internal_valid  $end
$var wire     64 1    selected_block [63:0] $end

$scope module block_selector $end
$var wire      1 (    d [3] $end
$var wire      1 )    d [2] $end
$var wire      1 *    d [1] $end
$var wire      1 +    d [0] $end
$var wire      1 ,    q [1] $end
$var wire      1 -    q [0] $end
$var wire      1 /    v  $end
$upscope $end


$scope module internal_pe $end
$var wire     64 1    d [63:0] $end
$var wire      6 .    q [5:0] $end
$var wire      1 0    v  $end
$var wire      1 2    dor [15] $end
$var wire      1 3    dor [14] $end
$var wire      1 4    dor [13] $end
$var wire      1 5    dor [12] $end
$var wire      1 6    dor [11] $end
$var wire      1 7    dor [10] $end
$var wire      1 8    dor [9] $end
$var wire      1 9    dor [8] $end
$var wire      1 :    dor [7] $end
$var wire      1 ;    dor [6] $end
$var wire      1 <    dor [5] $end
$var wire      1 =    dor [4] $end
$var wire      1 >    dor [3] $end
$var wire      1 ?    dor [2] $end
$var wire      1 @    dor [1] $end
$var wire      1 A    dor [0] $end
$var wire      4 B    row_index [3:0] $end
$var wire      4 C    column_data [3:0] $end
$var wire      1 D    col_index [1] $end
$var wire      1 E    col_index [0] $end
$var wire      1 F    row_valid  $end
$var wire      4 G    mux_stage1_out0 [3:0] $end
$var wire      4 H    mux_stage1_out1 [3:0] $end
$var wire      4 I    mux_stage1_out2 [3:0] $end
$var wire      4 J    mux_stage1_out3 [3:0] $end

$scope begin row_or_logic[0] $end
$var parameter 32 K    i [31:0] $end
$upscope $end


$scope begin row_or_logic[1] $end
$var parameter 32 L    i [31:0] $end
$upscope $end


$scope begin row_or_logic[2] $end
$var parameter 32 M    i [31:0] $end
$upscope $end


$scope begin row_or_logic[3] $end
$var parameter 32 N    i [31:0] $end
$upscope $end


$scope begin row_or_logic[4] $end
$var parameter 32 O    i [31:0] $end
$upscope $end


$scope begin row_or_logic[5] $end
$var parameter 32 P    i [31:0] $end
$upscope $end


$scope begin row_or_logic[6] $end
$var parameter 32 Q    i [31:0] $end
$upscope $end


$scope begin row_or_logic[7] $end
$var parameter 32 R    i [31:0] $end
$upscope $end


$scope begin row_or_logic[8] $end
$var parameter 32 S    i [31:0] $end
$upscope $end


$scope begin row_or_logic[9] $end
$var parameter 32 T    i [31:0] $end
$upscope $end


$scope begin row_or_logic[10] $end
$var parameter 32 U    i [31:0] $end
$upscope $end


$scope begin row_or_logic[11] $end
$var parameter 32 V    i [31:0] $end
$upscope $end


$scope begin row_or_logic[12] $end
$var parameter 32 W    i [31:0] $end
$upscope $end


$scope begin row_or_logic[13] $end
$var parameter 32 X    i [31:0] $end
$upscope $end


$scope begin row_or_logic[14] $end
$var parameter 32 Y    i [31:0] $end
$upscope $end


$scope begin row_or_logic[15] $end
$var parameter 32 Z    i [31:0] $end
$upscope $end


$scope module row_encoder $end
$var wire      1 2    d [15] $end
$var wire      1 3    d [14] $end
$var wire      1 4    d [13] $end
$var wire      1 5    d [12] $end
$var wire      1 6    d [11] $end
$var wire      1 7    d [10] $end
$var wire      1 8    d [9] $end
$var wire      1 9    d [8] $end
$var wire      1 :    d [7] $end
$var wire      1 ;    d [6] $end
$var wire      1 <    d [5] $end
$var wire      1 =    d [4] $end
$var wire      1 >    d [3] $end
$var wire      1 ?    d [2] $end
$var wire      1 @    d [1] $end
$var wire      1 A    d [0] $end
$var wire      4 B    q [3:0] $end
$var wire      1 F    v  $end
$var wire      1 [    row_status [3] $end
$var wire      1 \    row_status [2] $end
$var wire      1 ]    row_status [1] $end
$var wire      1 ^    row_status [0] $end
$var wire      1 _    row_index [1] $end
$var wire      1 `    row_index [0] $end
$var wire      1 a    col_index [1] $end
$var wire      1 b    col_index [0] $end
$var wire      1 c    row_valid  $end
$var wire      4 d    selected_row [3:0] $end

$scope module row_pe $end
$var wire      1 [    d [3] $end
$var wire      1 \    d [2] $end
$var wire      1 ]    d [1] $end
$var wire      1 ^    d [0] $end
$var wire      1 _    q [1] $end
$var wire      1 `    q [0] $end
$var wire      1 c    v  $end
$upscope $end


$scope module col_pe $end
$var wire      4 d    d [3:0] $end
$var wire      1 a    q [1] $end
$var wire      1 b    q [0] $end
$var wire      1 e    v  $end
$upscope $end

$upscope $end


$scope module col_encoder $end
$var wire      4 C    d [3:0] $end
$var wire      1 D    q [1] $end
$var wire      1 E    q [0] $end
$var wire      1 f    v  $end
$upscope $end

$upscope $end

$upscope $end


$scope function get_expected_q $end
$var reg       8 g    get_expected_q [7:0] $end
$var reg      256 h    d [255:0] $end
$var integer  32 i    i  $end
$upscope $end

$upscope $end

$enddefinitions $end
$dumpvars
b1111 Z
b1110 Y
b1101 X
b1100 W
b1011 V
b1010 U
b1001 T
b1000 S
b111 R
b110 Q
b101 P
b100 O
b11 N
b10 M
b1 L
b0 K
b0 !
b0 "
0#
b0 $
bx %
bx &
b0 '
0(
0)
0*
0+
0,
0-
b0 .
0/
00
b0 1
02
03
04
05
06
07
08
09
0:
0;
0<
0=
0>
0?
0@
0A
b0 B
b0 C
0D
0E
0F
b0 G
b0 H
b0 I
b0 J
0[
0\
0]
0^
0_
0`
0a
0b
0c
b0 d
0e
0f
bx g
bx h
bx i
$end
#10000
b0 &
b1 !
b0 %
b1 '
1+
b1 1
1A
b1 G
1/
1#
b1 C
1^
b1 d
1e
1c
1f
1F
10
#20000
b1 &
b0 !
b10 !
b1 %
b10 '
b10 1
b10 G
b10 C
1E
b1 .
b1 "
#30000
b10 &
b0 !
b100 !
b10 %
b100 '
b100 1
b100 G
b100 C
1D
0E
b10 .
b10 "
#40000
b11 &
b0 !
b1000 !
b11 %
b1000 '
b1000 1
b1000 G
b1000 C
1E
b11 .
b11 "
#50000
b100 &
b0 !
b10000 !
b100 %
b10000 '
b10000 1
0A
1@
b0 G
b0 C
b10 d
1b
0D
0E
0f
b0 .
b1 B
b1 G
b100 .
b0 "
b100 "
b1 C
1f
#60000
b101 &
b0 !
b100000 !
b101 %
b100000 '
b100000 1
b10 G
b10 C
1E
b101 .
b101 "
#70000
b110 &
b0 !
b1000000 !
b110 %
b1000000 '
b1000000 1
b100 G
b100 C
1D
0E
b110 .
b110 "
#80000
b111 &
b0 !
b10000000 !
b111 %
b10000000 '
b10000000 1
b1000 G
b1000 C
1E
b111 .
b111 "
#90000
b1000 &
b0 !
b100000000 !
b1000 %
b100000000 '
b100000000 1
0@
1?
b0 G
b0 C
b100 d
1a
0b
0D
0E
0f
b100 .
b10 B
b1 G
b1000 .
b100 "
b1000 "
b1 C
1f
#100000
b1001 &
b0 !
b1000000000 !
b1001 %
b1000000000 '
b1000000000 1
b10 G
b10 C
1E
b1001 .
b1001 "
#110000
b1010 &
b0 !
b10000000000 !
b1010 %
b10000000000 '
b10000000000 1
b100 G
b100 C
1D
0E
b1010 .
b1010 "
#120000
b1011 &
b0 !
b100000000000 !
b1011 %
b100000000000 '
b100000000000 1
b1000 G
b1000 C
1E
b1011 .
b1011 "
#130000
b1100 &
b0 !
b1000000000000 !
b1100 %
b1000000000000 '
b1000000000000 1
0?
1>
b0 G
b0 C
b1000 d
1b
0D
0E
0f
b1000 .
b11 B
b1 G
b1100 .
b1000 "
b1100 "
b1 C
1f
#140000
b1101 &
b0 !
b10000000000000 !
b1101 %
b10000000000000 '
b10000000000000 1
b10 G
b10 C
1E
b1101 .
b1101 "
#150000
b1110 &
b0 !
b100000000000000 !
b1110 %
b100000000000000 '
b100000000000000 1
b100 G
b100 C
1D
0E
b1110 .
b1110 "
#160000
b1111 &
b0 !
b1000000000000000 !
b1111 %
b1000000000000000 '
b1000000000000000 1
b1000 G
b1000 C
1E
b1111 .
b1111 "
#170000
b10000 &
b0 !
b10000000000000000 !
b10000 %
b10000000000000000 '
b10000000000000000 1
0>
1=
b0 G
b0 C
1]
0^
b0 d
1`
b1 d
b111 B
0a
0b
0e
0D
0E
0f
b100 B
b11100 .
1e
b11100 "
b1 H
b10000 .
b10000 "
b1 C
1f
#180000
b10001 &
b0 !
b100000000000000000 !
b10001 %
b100000000000000000 '
b100000000000000000 1
b10 H
b10 C
1E
b10001 .
b10001 "
#190000
b10010 &
b0 !
b1000000000000000000 !
b10010 %
b1000000000000000000 '
b1000000000000000000 1
b100 H
b100 C
1D
0E
b10010 .
b10010 "
#200000
b10011 &
b0 !
b10000000000000000000 !
b10011 %
b10000000000000000000 '
b10000000000000000000 1
b1000 H
b1000 C
1E
b10011 .
b10011 "
#210000
b10100 &
b0 !
b100000000000000000000 !
b10100 %
b100000000000000000000 '
b100000000000000000000 1
0=
1<
b0 H
b0 C
b10 d
1b
0D
0E
0f
b10000 .
b101 B
b1 H
b10100 .
b10000 "
b10100 "
b1 C
1f
#220000
b10101 &
b0 !
b1000000000000000000000 !
b10101 %
b1000000000000000000000 '
b1000000000000000000000 1
b10 H
b10 C
1E
b10101 .
b10101 "
#230000
b10110 &
b0 !
b10000000000000000000000 !
b10110 %
b10000000000000000000000 '
b10000000000000000000000 1
b100 H
b100 C
1D
0E
b10110 .
b10110 "
#240000
b10111 &
b0 !
b100000000000000000000000 !
b10111 %
b100000000000000000000000 '
b100000000000000000000000 1
b1000 H
b1000 C
1E
b10111 .
b10111 "
#250000
b11000 &
b0 !
b1000000000000000000000000 !
b11000 %
b1000000000000000000000000 '
b1000000000000000000000000 1
0<
1;
b0 H
b0 C
b100 d
1a
0b
0D
0E
0f
b10100 .
b110 B
b1 H
b11000 .
b10100 "
b11000 "
b1 C
1f
#260000
b11001 &
b0 !
b10000000000000000000000000 !
b11001 %
b10000000000000000000000000 '
b10000000000000000000000000 1
b10 H
b10 C
1E
b11001 .
b11001 "
#270000
b11010 &
b0 !
b100000000000000000000000000 !
b11010 %
b100000000000000000000000000 '
b100000000000000000000000000 1
b100 H
b100 C
1D
0E
b11010 .
b11010 "
#280000
b11011 &
b0 !
b1000000000000000000000000000 !
b11011 %
b1000000000000000000000000000 '
b1000000000000000000000000000 1
b1000 H
b1000 C
1E
b11011 .
b11011 "
#290000
b11100 &
b0 !
b10000000000000000000000000000 !
b11100 %
b10000000000000000000000000000 '
b10000000000000000000000000000 1
0;
1:
b0 H
b0 C
b1000 d
1b
0D
0E
0f
b11000 .
b111 B
b1 H
b11100 .
b11000 "
b11100 "
b1 C
1f
#300000
b11101 &
b0 !
b100000000000000000000000000000 !
b11101 %
b100000000000000000000000000000 '
b100000000000000000000000000000 1
b10 H
b10 C
1E
b11101 .
b11101 "
#310000
b11110 &
b0 !
b1000000000000000000000000000000 !
b11110 %
b1000000000000000000000000000000 '
b1000000000000000000000000000000 1
b100 H
b100 C
1D
0E
b11110 .
b11110 "
#320000
b11111 &
b0 !
b10000000000000000000000000000000 !
b11111 %
b10000000000000000000000000000000 '
b10000000000000000000000000000000 1
b1000 H
b1000 C
1E
b11111 .
b11111 "
#330000
b100000 &
b0 !
b100000000000000000000000000000000 !
b100000 %
b100000000000000000000000000000000 '
b100000000000000000000000000000000 1
0:
19
b0 H
b0 C
1\
0]
b0 d
0`
1_
b1 d
b1011 B
0a
0b
0e
0D
0E
0f
b1000 B
b101100 .
1e
b101100 "
b1 I
b100000 .
b100000 "
b1 C
1f
#340000
b100001 &
b0 !
b1000000000000000000000000000000000 !
b100001 %
b1000000000000000000000000000000000 '
b1000000000000000000000000000000000 1
b10 I
b10 C
1E
b100001 .
b100001 "
#350000
b100010 &
b0 !
b10000000000000000000000000000000000 !
b100010 %
b10000000000000000000000000000000000 '
b10000000000000000000000000000000000 1
b100 I
b100 C
1D
0E
b100010 .
b100010 "
#360000
b100011 &
b0 !
b100000000000000000000000000000000000 !
b100011 %
b100000000000000000000000000000000000 '
b100000000000000000000000000000000000 1
b1000 I
b1000 C
1E
b100011 .
b100011 "
#370000
b100100 &
b0 !
b1000000000000000000000000000000000000 !
b100100 %
b1000000000000000000000000000000000000 '
b1000000000000000000000000000000000000 1
09
18
b0 I
b0 C
b10 d
1b
0D
0E
0f
b100000 .
b1001 B
b1 I
b100100 .
b100000 "
b100100 "
b1 C
1f
#380000
b100101 &
b0 !
b10000000000000000000000000000000000000 !
b100101 %
b10000000000000000000000000000000000000 '
b10000000000000000000000000000000000000 1
b10 I
b10 C
1E
b100101 .
b100101 "
#390000
b100110 &
b0 !
b100000000000000000000000000000000000000 !
b100110 %
b100000000000000000000000000000000000000 '
b100000000000000000000000000000000000000 1
b100 I
b100 C
1D
0E
b100110 .
b100110 "
#400000
b100111 &
b0 !
b1000000000000000000000000000000000000000 !
b100111 %
b1000000000000000000000000000000000000000 '
b1000000000000000000000000000000000000000 1
b1000 I
b1000 C
1E
b100111 .
b100111 "
#410000
b101000 &
b0 !
b10000000000000000000000000000000000000000 !
b101000 %
b10000000000000000000000000000000000000000 '
b10000000000000000000000000000000000000000 1
08
17
b0 I
b0 C
b100 d
1a
0b
0D
0E
0f
b100100 .
b1010 B
b1 I
b101000 .
b100100 "
b101000 "
b1 C
1f
#420000
b101001 &
b0 !
b100000000000000000000000000000000000000000 !
b101001 %
b100000000000000000000000000000000000000000 '
b100000000000000000000000000000000000000000 1
b10 I
b10 C
1E
b101001 .
b101001 "
#430000
b101010 &
b0 !
b1000000000000000000000000000000000000000000 !
b101010 %
b1000000000000000000000000000000000000000000 '
b1000000000000000000000000000000000000000000 1
b100 I
b100 C
1D
0E
b101010 .
b101010 "
#440000
b101011 &
b0 !
b10000000000000000000000000000000000000000000 !
b101011 %
b10000000000000000000000000000000000000000000 '
b10000000000000000000000000000000000000000000 1
b1000 I
b1000 C
1E
b101011 .
b101011 "
#450000
b101100 &
b0 !
b100000000000000000000000000000000000000000000 !
b101100 %
b100000000000000000000000000000000000000000000 '
b100000000000000000000000000000000000000000000 1
07
16
b0 I
b0 C
b1000 d
1b
0D
0E
0f
b101000 .
b1011 B
b1 I
b101100 .
b101000 "
b101100 "
b1 C
1f
#460000
b101101 &
b0 !
b1000000000000000000000000000000000000000000000 !
b101101 %
b1000000000000000000000000000000000000000000000 '
b1000000000000000000000000000000000000000000000 1
b10 I
b10 C
1E
b101101 .
b101101 "
#470000
b101110 &
b0 !
b10000000000000000000000000000000000000000000000 !
b101110 %
b10000000000000000000000000000000000000000000000 '
b10000000000000000000000000000000000000000000000 1
b100 I
b100 C
1D
0E
b101110 .
b101110 "
#480000
b101111 &
b0 !
b100000000000000000000000000000000000000000000000 !
b101111 %
b100000000000000000000000000000000000000000000000 '
b100000000000000000000000000000000000000000000000 1
b1000 I
b1000 C
1E
b101111 .
b101111 "
#490000
b110000 &
b0 !
b1000000000000000000000000000000000000000000000000 !
b110000 %
b1000000000000000000000000000000000000000000000000 '
b1000000000000000000000000000000000000000000000000 1
06
15
b0 I
b0 C
1[
0\
b0 d
1`
b1 d
b1111 B
0a
0b
0e
0D
0E
0f
b1100 B
b111100 .
1e
b111100 "
b1 J
b110000 .
b110000 "
b1 C
1f
#500000
b110001 &
b0 !
b10000000000000000000000000000000000000000000000000 !
b110001 %
b10000000000000000000000000000000000000000000000000 '
b10000000000000000000000000000000000000000000000000 1
b10 J
b10 C
1E
b110001 .
b110001 "
#510000
b110010 &
b0 !
b100000000000000000000000000000000000000000000000000 !
b110010 %
b100000000000000000000000000000000000000000000000000 '
b100000000000000000000000000000000000000000000000000 1
b100 J
b100 C
1D
0E
b110010 .
b110010 "
#520000
b110011 &
b0 !
b1000000000000000000000000000000000000000000000000000 !
b110011 %
b1000000000000000000000000000000000000000000000000000 '
b1000000000000000000000000000000000000000000000000000 1
b1000 J
b1000 C
1E
b110011 .
b110011 "
#530000
b110100 &
b0 !
b10000000000000000000000000000000000000000000000000000 !
b110100 %
b10000000000000000000000000000000000000000000000000000 '
b10000000000000000000000000000000000000000000000000000 1
05
14
b0 J
b0 C
b10 d
1b
0D
0E
0f
b110000 .
b1101 B
b1 J
b110100 .
b110000 "
b110100 "
b1 C
1f
#540000
b110101 &
b0 !
b100000000000000000000000000000000000000000000000000000 !
b110101 %
b100000000000000000000000000000000000000000000000000000 '
b100000000000000000000000000000000000000000000000000000 1
b10 J
b10 C
1E
b110101 .
b110101 "
#550000
b110110 &
b0 !
b1000000000000000000000000000000000000000000000000000000 !
b110110 %
b1000000000000000000000000000000000000000000000000000000 '
b1000000000000000000000000000000000000000000000000000000 1
b100 J
b100 C
1D
0E
b110110 .
b110110 "
#560000
b110111 &
b0 !
b10000000000000000000000000000000000000000000000000000000 !
b110111 %
b10000000000000000000000000000000000000000000000000000000 '
b10000000000000000000000000000000000000000000000000000000 1
b1000 J
b1000 C
1E
b110111 .
b110111 "
#570000
b111000 &
b0 !
b100000000000000000000000000000000000000000000000000000000 !
b111000 %
b100000000000000000000000000000000000000000000000000000000 '
b100000000000000000000000000000000000000000000000000000000 1
04
13
b0 J
b0 C
b100 d
1a
0b
0D
0E
0f
b110100 .
b1110 B
b1 J
b111000 .
b110100 "
b111000 "
b1 C
1f
#580000
b111001 &
b0 !
b1000000000000000000000000000000000000000000000000000000000 !
b111001 %
b1000000000000000000000000000000000000000000000000000000000 '
b1000000000000000000000000000000000000000000000000000000000 1
b10 J
b10 C
1E
b111001 .
b111001 "
#590000
b111010 &
b0 !
b10000000000000000000000000000000000000000000000000000000000 !
b111010 %
b10000000000000000000000000000000000000000000000000000000000 '
b10000000000000000000000000000000000000000000000000000000000 1
b100 J
b100 C
1D
0E
b111010 .
b111010 "
#600000
b111011 &
b0 !
b100000000000000000000000000000000000000000000000000000000000 !
b111011 %
b100000000000000000000000000000000000000000000000000000000000 '
b100000000000000000000000000000000000000000000000000000000000 1
b1000 J
b1000 C
1E
b111011 .
b111011 "
#610000
b111100 &
b0 !
b1000000000000000000000000000000000000000000000000000000000000 !
b111100 %
b1000000000000000000000000000000000000000000000000000000000000 '
b1000000000000000000000000000000000000000000000000000000000000 1
03
12
b0 J
b0 C
b1000 d
1b
0D
0E
0f
b111000 .
b1111 B
b1 J
b111100 .
b111000 "
b111100 "
b1 C
1f
#620000
b111101 &
b0 !
b10000000000000000000000000000000000000000000000000000000000000 !
b111101 %
b10000000000000000000000000000000000000000000000000000000000000 '
b10000000000000000000000000000000000000000000000000000000000000 1
b10 J
b10 C
1E
b111101 .
b111101 "
#630000
b111110 &
b0 !
b100000000000000000000000000000000000000000000000000000000000000 !
b111110 %
b100000000000000000000000000000000000000000000000000000000000000 '
b100000000000000000000000000000000000000000000000000000000000000 1
b100 J
b100 C
1D
0E
b111110 .
b111110 "
#640000
b111111 &
b0 !
b1000000000000000000000000000000000000000000000000000000000000000 !
b111111 %
b1000000000000000000000000000000000000000000000000000000000000000 '
b1000000000000000000000000000000000000000000000000000000000000000 1
b1000 J
b1000 C
1E
b111111 .
b111111 "
#650000
b1000000 &
b0 !
b10000000000000000000000000000000000000000000000000000000000000000 !
b1000000 %
b10000000000000000000000000000000000000000000000000000000000000000 '
0+
1*
b0 1
1-
b1 1
b1111111 "
02
b0 J
b0 C
0[
b0 d
1A
0`
0_
b11 B
1^
b1 d
0a
0b
0e
0c
0D
0E
0f
0F
00
b0 B
1e
1c
b1100 .
1F
10
b1001100 "
b1 G
b0 .
b1000000 "
b1 C
1f
#660000
b1000001 &
b0 !
b100000000000000000000000000000000000000000000000000000000000000000 !
b1000001 %
b100000000000000000000000000000000000000000000000000000000000000000 '
b10 1
b10 G
b10 C
1E
b1 .
b1000001 "
