Unscalable PE64/Unscalable_PE64 (main - 90nm)/Code Files/priority.v
module pe64_if_else (
    input  wire [63:0] d,
    output reg  [5:0]  q,
    output wire        v
);
    always @(*) begin
        if      (d[63]) q = 6'd63;
        else if (d[62]) q = 6'd62;
        else if (d[61]) q = 6'd61;
        else if (d[60]) q = 6'd60;
        else if (d[59]) q = 6'd59;
        else if (d[58]) q = 6'd58;
        else if (d[57]) q = 6'd57;
        else if (d[56]) q = 6'd56;
        else if (d[55]) q = 6'd55;
        else if (d[54]) q = 6'd54;
        else if (d[53]) q = 6'd53;
        else if (d[52]) q = 6'd52;
        else if (d[51]) q = 6'd51;
        else if (d[50]) q = 6'd50;
        else if (d[49]) q = 6'd49;
        else if (d[48]) q = 6'd48;
        else if (d[47]) q = 6'd47;
        else if (d[46]) q = 6'd46;
        else if (d[45]) q = 6'd45;
        else if (d[44]) q = 6'd44;
        else if (d[43]) q = 6'd43;
        else if (d[42]) q = 6'd42;
        else if (d[41]) q = 6'd41;
        else if (d[40]) q = 6'd40;
        else if (d[39]) q = 6'd39;
        else if (d[38]) q = 6'd38;
        else if (d[37]) q = 6'd37;
        else if (d[36]) q = 6'd36;
        else if (d[35]) q = 6'd35;
        else if (d[34]) q = 6'd34;
        else if (d[33]) q = 6'd33;
        else if (d[32]) q = 6'd32;
        else if (d[31]) q = 6'd31;
        else if (d[30]) q = 6'd30;
        else if (d[29]) q = 6'd29;
        else if (d[28]) q = 6'd28;
        else if (d[27]) q = 6'd27;
        else if (d[26]) q = 6'd26;
        else if (d[25]) q = 6'd25;
        else if (d[24]) q = 6'd24;
        else if (d[23]) q = 6'd23;
        else if (d[22]) q = 6'd22;
        else if (d[21]) q = 6'd21;
        else if (d[20]) q = 6'd20;
        else if (d[19]) q = 6'd19;
        else if (d[18]) q = 6'd18;
        else if (d[17]) q = 6'd17;
        else if (d[16]) q = 6'd16;
        else if (d[15]) q = 6'd15;
        else if (d[14]) q = 6'd14;
        else if (d[13]) q = 6'd13;
        else if (d[12]) q = 6'd12;
        else if (d[11]) q = 6'd11;
        else if (d[10]) q = 6'd10;
        else if (d[9])  q = 6'd9;
        else if (d[8])  q = 6'd8;
        else if (d[7])  q = 6'd7;
        else if (d[6])  q = 6'd6;
        else if (d[5])  q = 6'd5;
        else if (d[4])  q = 6'd4;
        else if (d[3])  q = 6'd3;
        else if (d[2])  q = 6'd2;
        else if (d[1])  q = 6'd1;
        else if (d[0])  q = 6'd0;
        else            q = 6'd0;
    end
    
    assign v = |d;
endmodule


module pe256_from_64 (
    input  wire [255:0] d,
    output reg  [7:0]   q,
    output wire         v
);

    wire [5:0] q0, q1, q2, q3;
    wire       v0, v1, v2, v3;

    pe64_if_else pe3 ( .d(d[255:192]), .q(q3), .v(v3) );
    pe64_if_else pe2 ( .d(d[191:128]), .q(q2), .v(v2) );
    pe64_if_else pe1 ( .d(d[127:64]),  .q(q1), .v(v1) );
    pe64_if_else pe0 ( .d(d[63:0]),    .q(q0), .v(v0) );

    always @(*) begin
        if (v3) begin
            q = {2'b11, q3};
        end
        else if (v2) begin
            q = {2'b10, q2};
        end
        else if (v1) begin
            q = {2'b01, q1};
        end
        else begin
            q = {2'b00, q0};
        end
    end

    assign v = v3 | v2 | v1 | v0;

endmodule

Unscalable PE64/Unscalable_PE64 (main - 180nm)/Code Files/priority_tb.v
`timescale 1ns / 1ps
`include "priority.v"

module tb_pe256_selfchecking();

    reg  [255:0] tb_d;
    wire [7:0]   tb_q;
    wire         tb_v;

    integer error_count;
    reg [7:0] expected_q;
    integer i;

    pe256_from_64 dut (
        .d(tb_d),
        .q(tb_q),
        .v(tb_v)
    );

    // CORRECTED FUNCTION FOR VERILOG-2001
    function [7:0] get_expected_q(input [255:0] d);
        integer i;
        begin : find_bit_block // Named block for disable
            get_expected_q = 8'b0; // Default value if no bit is set
            for (i = 255; i >= 0; i = i - 1) begin
                if (d[i] == 1'b1) begin
                    get_expected_q = i; // Assign return value to function name
                    disable find_bit_block; // Exit the loop and function
                end
            end
        end
    endfunction

    initial begin
        $dumpfile("pe256.vcd");
        $dumpvars(0, tb_pe256_selfchecking);
        error_count = 0;
        
        tb_d = 256'b0;
        #10;
        if (tb_v !== 1'b0) begin
            $display("FAIL: All-zero input, but valid signal is high.");
            error_count = error_count + 1;
        end

        for (i = 0; i < 256; i = i + 1) begin
            tb_d = 0;
            tb_d[i] = 1'b1;
            expected_q = i;
            #10;
            if (tb_q !== expected_q || tb_v !== 1'b1) begin
                $display("FAIL: Input bit %0d | Expected: %0d | Got: %0d", i, expected_q, tb_q);
                error_count = error_count + 1;
            end
        end

        tb_d = 0;
        tb_d[123] = 1'b1;
        tb_d[200] = 1'b1;
        tb_d[5]   = 1'b1;
        expected_q = 200;
        #10;
        if (tb_q !== expected_q) begin
            $display("FAIL: Multi-bit test | Expected: %0d | Got: %0d", expected_q, tb_q);
            error_count = error_count + 1;
        end

        for (i = 0; i < 20; i = i + 1) begin
            tb_d = {$random, $random, $random, $random, $random, $random, $random, $random};
            expected_q = get_expected_q(tb_d);
            #10;
            if (tb_q !== expected_q) begin
                $display("FAIL: Random test | Input: %h | Expected: %0d | Got: %0d", tb_d, expected_q, tb_q);
                error_count = error_count + 1;
            end
        end

        #20;
        if (error_count == 0) begin
            $display("SUCCESS: All tests passed!");
        end else begin
            $display("FAILURE: %0d errors found.", error_count);
        end

        $finish;
    end

endmodule

Unscalable PE64/Unscalable_PE64 (main - 180nm)/Code Files/pe256.vcd
$date
    Oct 10, 2025  15:40:39
$end
$version
    TOOL:	ncsim(64)	15.20-s086
$end
$timescale
    1 ps
$end

$scope module tb_pe256_selfchecking $end
$var reg      256 !    tb_d [255:0] $end
$var wire      8 "    tb_q [7:0] $end
$var wire      1 #    tb_v  $end
$var integer  32 $    error_count  $end
$var reg       8 %    expected_q [7:0] $end
$var integer  32 &    i  $end

$scope module dut $end
$var wire     256 '    d [255:0] $end
$var reg       8 (    q [7:0] $end
$var wire      1 #    v  $end
$var wire      6 )    q0 [5:0] $end
$var wire      6 *    q1 [5:0] $end
$var wire      6 +    q2 [5:0] $end
$var wire      6 ,    q3 [5:0] $end
$var wire      1 -    v0  $end
$var wire      1 .    v1  $end
$var wire      1 /    v2  $end
$var wire      1 0    v3  $end

$scope module pe3 $end
$var wire     64 1    d [63:0] $end
$var reg       6 2    q [5:0] $end
$var wire      1 0    v  $end
$upscope $end


$scope module pe2 $end
$var wire     64 3    d [63:0] $end
$var reg       6 4    q [5:0] $end
$var wire      1 /    v  $end
$upscope $end


$scope module pe1 $end
$var wire     64 5    d [63:0] $end
$var reg       6 6    q [5:0] $end
$var wire      1 .    v  $end
$upscope $end


$scope module pe0 $end
$var wire     64 7    d [63:0] $end
$var reg       6 8    q [5:0] $end
$var wire      1 -    v  $end
$upscope $end

$upscope $end


$scope function get_expected_q $end
$var reg       8 9    get_expected_q [7:0] $end
$var reg      256 :    d [255:0] $end
$var integer  32 ;    i  $end
$upscope $end

$upscope $end

$enddefinitions $end
$dumpvars
b0 !
b0 "
0#
b0 $
bx %
bx &
b0 '
b0 (
b0 )
b0 *
b0 +
b0 ,
0-
0.
0/
00
b0 1
b0 2
b0 3
b0 4
b0 5
b0 6
b0 7
b0 8
bx 9
bx :
bx ;
$end
#10000
b0 &
b1 !
b0 %
b1 '
b1 7
1-
1#
#20000
b1 &
b0 !
b10 !
b1 %
b10 '
b10 7
b1 8
b1 )
b1 (
b1 "
#30000
b10 &
b0 !
b100 !
b10 %
b100 '
b100 7
b10 8
b10 )
b10 (
b10 "
#40000
b11 &
b0 !
b1000 !
b11 %
b1000 '
b1000 7
b11 8
b11 )
b11 (
b11 "
#50000
b100 &
b0 !
b10000 !
b100 %
b10000 '
b10000 7
b100 8
b100 )
b100 (
b100 "
#60000
b101 &
b0 !
b100000 !
b101 %
b100000 '
b100000 7
b101 8
b101 )
b101 (
b101 "
#70000
b110 &
b0 !
b1000000 !
b110 %
b1000000 '
b1000000 7
b110 8
b110 )
b110 (
b110 "
#80000
b111 &
b0 !
b10000000 !
b111 %
b10000000 '
b10000000 7
b111 8
b111 )
b111 (
b111 "
#90000
b1000 &
b0 !
b100000000 !
b1000 %
b100000000 '
b100000000 7
b1000 8
b1000 )
b1000 (
b1000 "
#100000
b1001 &
b0 !
b1000000000 !
b1001 %
b1000000000 '
b1000000000 7
b1001 8
b1001 )
b1001 (
b1001 "
#110000
b1010 &
b0 !
b10000000000 !
b1010 %
b10000000000 '
b10000000000 7
b1010 8
b1010 )
b1010 (
b1010 "
#120000
b1011 &
b0 !
b100000000000 !
b1011 %
b100000000000 '
b100000000000 7
b1011 8
b1011 )
b1011 (
b1011 "
#130000
b1100 &
b0 !
b1000000000000 !
b1100 %
b1000000000000 '
b1000000000000 7
b1100 8
b1100 )
b1100 (
b1100 "
#140000
b1101 &
b0 !
b10000000000000 !
b1101 %
b10000000000000 '
b10000000000000 7
b1101 8
b1101 )
b1101 (
b1101 "
#150000
b1110 &
b0 !
b100000000000000 !
b1110 %
b100000000000000 '
b100000000000000 7
b1110 8
b1110 )
b1110 (
b1110 "
#160000
b1111 &
b0 !
b1000000000000000 !
b1111 %
b1000000000000000 '
b1000000000000000 7
b1111 8
b1111 )
b1111 (
b1111 "
#170000
b10000 &
b0 !
b10000000000000000 !
b10000 %
b10000000000000000 '
b10000000000000000 7
b10000 8
b10000 )
b10000 (
b10000 "
#180000
b10001 &
b0 !
b100000000000000000 !
b10001 %
b100000000000000000 '
b100000000000000000 7
b10001 8
b10001 )
b10001 (
b10001 "
#190000
b10010 &
b0 !
b1000000000000000000 !
b10010 %
b1000000000000000000 '
b1000000000000000000 7
b10010 8
b10010 )
b10010 (
b10010 "
#200000
b10011 &
b0 !
b10000000000000000000 !
b10011 %
b10000000000000000000 '
b10000000000000000000 7
b10011 8
b10011 )
b10011 (
b10011 "
#210000
b10100 &
b0 !
b100000000000000000000 !
b10100 %
b100000000000000000000 '
b100000000000000000000 7
b10100 8
b10100 )
b10100 (
b10100 "
#220000
b10101 &
b0 !
b1000000000000000000000 !
b10101 %
b1000000000000000000000 '
b1000000000000000000000 7
b10101 8
b10101 )
b10101 (
b10101 "
#230000
b10110 &
b0 !
b10000000000000000000000 !
b10110 %
b10000000000000000000000 '
b10000000000000000000000 7
b10110 8
b10110 )
b10110 (
b10110 "
#240000
b10111 &
b0 !
b100000000000000000000000 !
b10111 %
b100000000000000000000000 '
b100000000000000000000000 7
b10111 8
b10111 )
b10111 (
b10111 "
#250000
b11000 &
b0 !
b1000000000000000000000000 !
b11000 %
b1000000000000000000000000 '
b1000000000000000000000000 7
b11000 8
b11000 )
b11000 (
b11000 "
#260000
b11001 &
b0 !
b10000000000000000000000000 !
b11001 %
b10000000000000000000000000 '
b10000000000000000000000000 7
b11001 8
b11001 )
b11001 (
b11001 "
#270000
b11010 &
b0 !
b100000000000000000000000000 !
b11010 %
b100000000000000000000000000 '
b100000000000000000000000000 7
b11010 8
b11010 )
b11010 (
b11010 "
#280000
b11011 &
b0 !
b1000000000000000000000000000 !
b11011 %
b1000000000000000000000000000 '
b1000000000000000000000000000 7
b11011 8
b11011 )
b11011 (
b11011 "
#290000
b11100 &
b0 !
b10000000000000000000000000000 !
b11100 %
b10000000000000000000000000000 '
b10000000000000000000000000000 7
b11100 8
b11100 )
b11100 (
b11100 "
#300000
b11101 &
b0 !
b100000000000000000000000000000 !
b11101 %
b100000000000000000000000000000 '
b100000000000000000000000000000 7
b11101 8
b11101 )
b11101 (
b11101 "
#310000
b11110 &
b0 !
b1000000000000000000000000000000 !
b11110 %
b1000000000000000000000000000000 '
b1000000000000000000000000000000 7
b11110 8
b11110 )
b11110 (
b11110 "
#320000
b11111 &
b0 !
b10000000000000000000000000000000 !
b11111 %
b10000000000000000000000000000000 '
b10000000000000000000000000000000 7
b11111 8
b11111 )
b11111 (
b11111 "
#330000
b100000 &
b0 !
b100000000000000000000000000000000 !
b100000 %
b100000000000000000000000000000000 '
b100000000000000000000000000000000 7
b100000 8
b100000 )
b100000 (
b100000 "
#340000
b100001 &
b0 !
b1000000000000000000000000000000000 !
b100001 %
b1000000000000000000000000000000000 '
b1000000000000000000000000000000000 7
b100001 8
b100001 )
b100001 (
b100001 "
#350000
b100010 &
b0 !
b10000000000000000000000000000000000 !
b100010 %
b10000000000000000000000000000000000 '
b10000000000000000000000000000000000 7
b100010 8
b100010 )
b100010 (
b100010 "
#360000
b100011 &
b0 !
b100000000000000000000000000000000000 !
b100011 %
b100000000000000000000000000000000000 '
b100000000000000000000000000000000000 7
b100011 8
b100011 )
b100011 (
b100011 "
#370000
b100100 &
b0 !
b1000000000000000000000000000000000000 !
b100100 %
b1000000000000000000000000000000000000 '
b1000000000000000000000000000000000000 7
b100100 8
b100100 )
b100100 (
b100100 "
#380000
b100101 &
b0 !
b10000000000000000000000000000000000000 !
b100101 %
b10000000000000000000000000000000000000 '
b10000000000000000000000000000000000000 7
b100101 8
b100101 )
b100101 (
b100101 "
#390000
b100110 &
b0 !
b100000000000000000000000000000000000000 !
b100110 %
b100000000000000000000000000000000000000 '
b100000000000000000000000000000000000000 7
b100110 8
b100110 )
b100110 (
b100110 "
#400000
b100111 &
b0 !
b1000000000000000000000000000000000000000 !
b100111 %
b1000000000000000000000000000000000000000 '
b1000000000000000000000000000000000000000 7
b100111 8
b100111 )
b100111 (
b100111 "
#410000
b101000 &
b0 !
b10000000000000000000000000000000000000000 !
b101000 %
b10000000000000000000000000000000000000000 '
b10000000000000000000000000000000000000000 7
b101000 8
b101000 )
b101000 (
b101000 "
#420000
b101001 &
b0 !
b100000000000000000000000000000000000000000 !
b101001 %
b100000000000000000000000000000000000000000 '
b100000000000000000000000000000000000000000 7
b101001 8
b101001 )
b101001 (
b101001 "
#430000
b101010 &
b0 !
b1000000000000000000000000000000000000000000 !
b101010 %
b1000000000000000000000000000000000000000000 '
b1000000000000000000000000000000000000000000 7
b101010 8
b101010 )
b101010 (
b101010 "
#440000
b101011 &
b0 !
b10000000000000000000000000000000000000000000 !
b101011 %
b10000000000000000000000000000000000000000000 '
b10000000000000000000000000000000000000000000 7
b101011 8
b101011 )
b101011 (
b101011 "
#450000
b101100 &
b0 !
b100000000000000000000000000000000000000000000 !
b101100 %
b100000000000000000000000000000000000000000000 '
b100000000000000000000000000000000000000000000 7
b101100 8
b101100 )
b101100 (
b101100 "
#460000
b101101 &
b0 !
b1000000000000000000000000000000000000000000000 !
b101101 %
b1000000000000000000000000000000000000000000000 '
b1000000000000000000000000000000000000000000000 7
b101101 8
b101101 )
b101101 (
b101101 "
#470000
b101110 &
b0 !
b10000000000000000000000000000000000000000000000 !
b101110 %
b10000000000000000000000000000000000000000000000 '
b10000000000000000000000000000000000000000000000 7
b101110 8
b101110 )
b101110 (
b101110 "
#480000
b101111 &
b0 !
b100000000000000000000000000000000000000000000000 !
b101111 %
b100000000000000000000000000000000000000000000000 '
b100000000000000000000000000000000000000000000000 7
b101111 8
b101111 )
b101111 (
b101111 "
#490000
b110000 &
b0 !
b1000000000000000000000000000000000000000000000000 !
b110000 %
b1000000000000000000000000000000000000000000000000 '
b1000000000000000000000000000000000000000000000000 7
b110000 8
b110000 )
b110000 (
b110000 "
#500000
b110001 &
b0 !
b10000000000000000000000000000000000000000000000000 !
b110001 %
b10000000000000000000000000000000000000000000000000 '
b10000000000000000000000000000000000000000000000000 7
b110001 8
b110001 )
b110001 (
b110001 "
#510000
b110010 &
b0 !
b100000000000000000000000000000000000000000000000000 !
b110010 %
b100000000000000000000000000000000000000000000000000 '
b100000000000000000000000000000000000000000000000000 7
b110010 8
b110010 )
b110010 (
b110010 "
#520000
b110011 &
b0 !
b1000000000000000000000000000000000000000000000000000 !
b110011 %
b1000000000000000000000000000000000000000000000000000 '
b1000000000000000000000000000000000000000000000000000 7
b110011 8
b110011 )
b110011 (
b110011 "
#530000
b110100 &
b0 !
b10000000000000000000000000000000000000000000000000000 !
b110100 %
b10000000000000000000000000000000000000000000000000000 '
b10000000000000000000000000000000000000000000000000000 7
b110100 8
b110100 )
b110100 (
b110100 "
#540000
b110101 &
b0 !
b100000000000000000000000000000000000000000000000000000 !
b110101 %
b100000000000000000000000000000000000000000000000000000 '
b100000000000000000000000000000000000000000000000000000 7
b110101 8
b110101 )
b110101 (
b110101 "
#550000
b110110 &
b0 !
b1000000000000000000000000000000000000000000000000000000 !
b110110 %
b1000000000000000000000000000000000000000000000000000000 '
b1000000000000000000000000000000000000000000000000000000 7
b110110 8
b110110 )
b110110 (
b110110 "
#560000
b110111 &
b0 !
b10000000000000000000000000000000000000000000000000000000 !
b110111 %
b10000000000000000000000000000000000000000000000000000000 '
b10000000000000000000000000000000000000000000000000000000 7
b110111 8
b110111 )
b110111 (
b110111 "
#570000
b111000 &
b0 !
b100000000000000000000000000000000000000000000000000000000 !
b111000 %
b100000000000000000000000000000000000000000000000000000000 '
b100000000000000000000000000000000000000000000000000000000 7
b111000 8
b111000 )
b111000 (
b111000 "
#580000
b111001 &
b0 !
b1000000000000000000000000000000000000000000000000000000000 !
b111001 %
b1000000000000000000000000000000000000000000000000000000000 '
b1000000000000000000000000000000000000000000000000000000000 7
b111001 8
b111001 )
b111001 (
b111001 "
#590000
b111010 &
b0 !
b10000000000000000000000000000000000000000000000000000000000 !
b111010 %
b10000000000000000000000000000000000000000000000000000000000 '
b10000000000000000000000000000000000000000000000000000000000 7
b111010 8
b111010 )
b111010 (
b111010 "
#600000
b111011 &
b0 !
b100000000000000000000000000000000000000000000000000000000000 !
b111011 %
b100000000000000000000000000000000000000000000000000000000000 '
b100000000000000000000000000000000000000000000000000000000000 7
b111011 8
b111011 )
b111011 (
b111011 "
#610000
b111100 &
b0 !
b1000000000000000000000000000000000000000000000000000000000000 !
b111100 %
b1000000000000000000000000000000000000000000000000000000000000 '
b1000000000000000000000000000000000000000000000000000000000000 7
b111100 8
b111100 )
b111100 (
b111100 "
#620000
b111101 &
b0 !
b10000000000000000000000000000000000000000000000000000000000000 !
b111101 %
b10000000000000000000000000000000000000000000000000000000000000 '
b10000000000000000000000000000000000000000000000000000000000000 7
b111101 8
b111101 )
b111101 (
b111101 "
#630000
b111110 &
b0 !
b100000000000000000000000000000000000000000000000000000000000000 !
b111110 %
b100000000000000000000000000000000000000000000000000000000000000 '
b100000000000000000000000000000000000000000000000000000000000000 7
b111110 8
b111110 )
b111110 (
b111110 "
#640000
b111111 &
b0 !
b1000000000000000000000000000000000000000000000000000000000000000 !
b111111 %
b1000000000000000000000000000000000000000000000000000000000000000 '
b1000000000000000000000000000000000000000000000000000000000000000 7
b111111 8
b111111 )
b111111 (
b111111 "
#650000
b1000000 &
b0 !
b10000000000000000000000000000000000000000000000000000000000000000 !
b1000000 %
b10000000000000000000000000000000000000000000000000000000000000000 '
b1 5
b0 7
b0 8
b0 )
0-
1.
b1000000 (
b1000000 "
#660000
b1000001 &
b0 !
b100000000000000000000000000000000000000000000000000000000000000000 !
b1000001 %
b100000000000000000000000000000000000000000000000000000000000000000 '
b10 5
b1 6
b1 *
b1000001 (
b1000001 "
#670000
b1000010 &
b0 !
b1000000000000000000000000000000000000000000000000000000000000000000 !
b1000010 %
b1000000000000000000000000000000000000000000000000000000000000000000 '
b100 5
b10 6
b10 *
b1000010 (
b1000010 "
#680000
b1000011 &
b0 !
b10000000000000000000000000000000000000000000000000000000000000000000 !
b1000011 %
b10000000000000000000000000000000000000000000000000000000000000000000 '
b1000 5
b11 6
b11 *
b1000011 (
b1000011 "
#690000
b1000100 &
b0 !
b100000000000000000000000000000000000000000000000000000000000000000000 !
b1000100 %
b100000000000000000000000000000000000000000000000000000000000000000000 '
b10000 5
b100 6
b100 *
b1000100 (
b1000100 "
#700000
b1000101 &
b0 !
b1000000000000000000000000000000000000000000000000000000000000000000000 !
b1000101 %
b1000000000000000000000000000000000000000000000000000000000000000000000 '
b100000 5
b101 6
b101 *
b1000101 (
b1000101 "
#710000
b1000110 &
b0 !
b10000000000000000000000000000000000000000000000000000000000000000000000 !
b1000110 %
b10000000000000000000000000000000000000000000000000000000000000000000000 '
b1000000 5
b110 6
b110 *
b1000110 (
b1000110 "
#720000
b1000111 &
b0 !
b100000000000000000000000000000000000000000000000000000000000000000000000 !
b1000111 %
b100000000000000000000000000000000000000000000000000000000000000000000000 '
b10000000 5
b111 6
b111 *
b1000111 (
b1000111 "
#730000
b1001000 &
b0 !
b1000000000000000000000000000000000000000000000000000000000000000000000000 !
b1001000 %
b1000000000000000000000000000000000000000000000000000000000000000000000000 '
b100000000 5
b1000 6
b1000 *
b1001000 (
b1001000 "
#740000
b1001001 &
b0 !
b10000000000000000000000000000000000000000000000000000000000000000000000000 !
b1001001 %
b10000000000000000000000000000000000000000000000000000000000000000000000000 '
b1000000000 5
b1001 6
b1001 *
b1001001 (
b1001001 "
#750000
b1001010 &
b0 !
b100000000000000000000000000000000000000000000000000000000000000000000000000 !
b1001010 %
b100000000000000000000000000000000000000000000000000000000000000000000000000 '
b10000000000 5
b1010 6
b1010 *
b1001010 (
b1001010 "
#760000
b1001011 &
b0 !
b1000000000000000000000000000000000000000000000000000000000000000000000000000 !
b1001011 %
b1000000000000000000000000000000000000000000000000000000000000000000000000000 '
b100000000000 5
b1011 6
b1011 *
b1001011 (
b1001011 "
#770000
b1001100 &
b0 !
b10000000000000000000000000000000000000000000000000000000000000000000000000000 !
b1001100 %
b10000000000000000000000000000000000000000000000000000000000000000000000000000 '
b1000000000000 5
b1100 6
b1100 *
b1001100 (
b1001100 "
#780000
b1001101 &
b0 !
b100000000000000000000000000000000000000000000000000000000000000000000000000000 !
b1001101 %
b100000000000000000000000000000000000000000000000000000000000000000000000000000 '
b10000000000000 5
b1101 6
b1101 *
b1001101 (
b1001101 "
#790000
b1001110 &
b0 !
b1000000000000000000000000000000000000000000000000000000000000000000000000000000 !
b1001110 %
b1000000000000000000000000000000000000000000000000000000000000000000000000000000 '
b100000000000000 5
b1110 6
b1110 *
b1001110 (
b1001110 "
#800000
b1001111 &
b0 !
b10000000000000000000000000000000000000000000000000000000000000000000000000000000 !
b1001111 %
b10000000000000000000000000000000000000000000000000000000000000000000000000000000 '
b1000000000000000 5
b1111 6
b1111 *
b1001111 (
b1001111 "
#810000
b1010000 &
b0 !
b100000000000000000000000000000000000000000000000000000000000000000000000000000000 !
b1010000 %
b100000000000000000000000000000000000000000000000000000000000000000000000000000000 '
b10000000000000000 5
b10000 6
b10000 *
b1010000 (
b1010000 "
#820000
b1010001 &
b0 !
b1000000000000000000000000000000000000000000000000000000000000000000000000000000000 !
b1010001 %
b1000000000000000000000000000000000000000000000000000000000000000000000000000000000 '
b100000000000000000 5
b10001 6
b10001 *
b1010001 (
b1010001 "
#830000
b1010010 &
b0 !
b10000000000000000000000000000000000000000000000000000000000000000000000000000000000 !
b1010010 %
b10000000000000000000000000000000000000000000000000000000000000000000000000000000000 '
b1000000000000000000 5
b10010 6
b10010 *
b1010010 (
b1010010 "
#840000
b1010011 &
b0 !
b100000000000000000000000000000000000000000000000000000000000000000000000000000000000 !
b1010011 %
b100000000000000000000000000000000000000000000000000000000000000000000000000000000000 '
b10000000000000000000 5
b10011 6
b10011 *
b1010011 (
b1010011 "
#850000
b1010100 &
b0 !
b1000000000000000000000000000000000000000000000000000000000000000000000000000000000000 !
b1010100 %
b1000000000000000000000000000000000000000000000000000000000000000000000000000000000000 '
b100000000000000000000 5
b10100 6
b10100 *
b1010100 (
b1010100 "
#860000
b1010101 &
b0 !
b10000000000000000000000000000000000000000000000000000000000000000000000000000000000000 !
b1010101 %
b10000000000000000000000000000000000000000000000000000000000000000000000000000000000000 '
b1000000000000000000000 5
b10101 6
b10101 *
b1010101 (
b1010101 "
#870000
b1010110 &
b0 !
b100000000000000000000000000000000000000000000000000000000000000000000000000000000000000 !
b1010110 %
b100000000000000000000000000000000000000000000000000000000000000000000000000000000000000 '
b10000000000000000000000 5
b10110 6
b10110 *
b1010110 (
b1010110 "
#880000
b1010111 &
b0 !
b1000000000000000000000000000000000000000000000000000000000000000000000000000000000000000 !
b1010111 %
b1000000000000000000000000000000000000000000000000000000000000000000000000000000000000000 '
b100000000000000000000000 5
b10111 6
b10111 *
b1010111 (
b1010111 "
#890000
b1011000 &
b0 !
b10000000000000000000000000000000000000000000000000000000000000000000000000000000000000000 !
b1011000 %
b10000000000000000000000000000000000000000000000000000000000000000000000000000000000000000 '
b1000000000000000000000000 5
b11000 6
b11000 *
b1011000 (
b1011000 "
#900000
b1011001 &
b0 !
b100000000000000000000000000000000000000000000000000000000000000000000000000000000000000000 !
b1011001 %
b100000000000000000000000000000000000000000000000000000000000000000000000000000000000000000 '
b10000000000000000000000000 5
b11001 6
b11001 *
b1011001 (
b1011001 "
#910000
b1011010 &
b0 !
b1000000000000000000000000000000000000000000000000000000000000000000000000000000000000000000 !
b1011010 %
b1000000000000000000000000000000000000000000000000000000000000000000000000000000000000000000 '
b100000000000000000000000000 5
b11010 6
b11010 *
b1011010 (
b1011010 "
#920000
b1011011 &
b0 !
b10000000000000000000000000000000000000000000000000000000000000000000000000000000000000000000 !
b1011011 %
b10000000000000000000000000000000000000000000000000000000000000000000000000000000000000000000 '
b1000000000000000000000000000 5
b11011 6
b11011 *
b1011011 (
b1011011 "
#930000
b1011100 &
b0 !
b100000000000000000000000000000000000000000000000000000000000000000000000000000000000000000000 !
b1011100 %
b100000000000000000000000000000000000000000000000000000000000000000000000000000000000000000000 '
b10000000000000000000000000000 5
b11100 6
b11100 *
b1011100 (
b1011100 "
#940000
b1011101 &
b0 !
b1000000000000000000000000000000000000000000000000000000000000000000000000000000000000000000000 !
b1011101 %
b1000000000000000000000000000000000000000000000000000000000000000000000000000000000000000000000 '
b100000000000000000000000000000 5
b11101 6
b11101 *
b1011101 (
b1011101 "
#950000
b1011110 &
b0 !
b10000000000000000000000000000000000000000000000000000000000000000000000000000000000000000000000 !
b1011110 %
b10000000000000000000000000000000000000000000000000000000000000000000000000000000000000000000000 '
b1000000000000000000000000000000 5
b11110 6
b11110 *
b1011110 (
b1011110 "
#960000
b1011111 &
b0 !
b100000000000000000000000000000000000000000000000000000000000000000000000000000000000000000000000 !
b1011111 %
b100000000000000000000000000000000000000000000000000000000000000000000000000000000000000000000000 '
b10000000000000000000000000000000 5
b11111 6
b11111 *
b1011111 (
b1011111 "
#970000
b1100000 &
b0 !
b1000000000000000000000000000000000000000000000000000000000000000000000000000000000000000000000000 !
b1100000 %
b1000000000000000000000000000000000000000000000000000000000000000000000000000000000000000000000000 '
b100000000000000000000000000000000 5
b100000 6
b100000 *
b1100000 (
b1100000 "
#980000
b1100001 &
b0 !
b10000000000000000000000000000000000000000000000000000000000000000000000000000000000000000000000000 !
b1100001 %
b10000000000000000000000000000000000000000000000000000000000000000000000000000000000000000000000000 '
b1000000000000000000000000000000000 5
b100001 6
b100001 *
b1100001 (
b1100001 "
#990000
b1100010 &
b0 !
b100000000000000000000000000000000000000000000000000000000000000000000000000000000000000000000000000 !
b1100010 %
b100000000000000000000000000000000000000000000000000000000000000000000000000000000000000000000000000 '
b10000000000000000000000000000000000 5
b100010 6
b100010 *
b1100010 (
b1100010 "
#1000000
b1100011 &
b0 !
b1000000000000000000000000000000000000000000000000000000000000000000000000000000000000000000000000000 !
b1100011 %
b1000000000000000000000000000000000000000000000000000000000000000000000000000000000000000000000000000 '
b100000000000000000000000000000000000 5
b100011 6
b100011 *
b1100011 (
b1100011 "
#1010000
b1100100 &
b0 !
b10000000000000000000000000000000000000000000000000000000000000000000000000000000000000000000000000000 !
b1100100 %
b10000000000000000000000000000000000000000000000000000000000000000000000000000000000000000000000000000 '
b1000000000000000000000000000000000000 5
b100100 6
b100100 *
b1100100 (
b1100100 "
#1020000
b1100101 &
b0 !
b100000000000000000000000000000000000000000000000000000000000000000000000000000000000000000000000000000 !
b1100101 %
b100000000000000000000000000000000000000000000000000000000000000000000000000000000000000000000000000000 '
b10000000000000000000000000000000000000 5
b100101 6
b100101 *
b1100101 (
b1100101 "
#1030000
b1100110 &
b0 !
b1000000000000000000000000000000000000000000000000000000000000000000000000000000000000000000000000000000 !
b1100110 %
b1000000000000000000000000000000000000000000000000000000000000000000000000000000000000000000000000000000 '
b100000000000000000000000000000000000000 5
b100110 6
b100110 *
b1100110 (
b1100110 "
#1040000
b1100111 &
b0 !
b10000000000000000000000000000000000000000000000000000000000000000000000000000000000000000000000000000000 !
b1100111 %
b10000000000000000000000000000000000000000000000000000000000000000000000000000000000000000000000000000000 '
b1000000000000000000000000000000000000000 5
b100111 6
b100111 *
b1100111 (
b1100111 "
#1050000
b1101000 &
b0 !
b100000000000000000000000000000000000000000000000000000000000000000000000000000000000000000000000000000000 !
b1101000 %
b100000000000000000000000000000000000000000000000000000000000000000000000000000000000000000000000000000000 '
b10000000000000000000000000000000000000000 5
b101000 6
b101000 *
b1101000 (
b1101000 "
#1060000
b1101001 &
b0 !
b1000000000000000000000000000000000000000000000000000000000000000000000000000000000000000000000000000000000 !
b1101001 %
b1000000000000000000000000000000000000000000000000000000000000000000000000000000000000000000000000000000000 '
b100000000000000000000000000000000000000000 5
b101001 6
b101001 *
b1101001 (
b1101001 "
#1070000
b1101010 &
b0 !
b10000000000000000000000000000000000000000000000000000000000000000000000000000000000000000000000000000000000 !
b1101010 %
b10000000000000000000000000000000000000000000000000000000000000000000000000000000000000000000000000000000000 '
b1000000000000000000000000000000000000000000 5
b101010 6
b101010 *
b1101010 (
b1101010 "
#1080000
b1101011 &
b0 !
b100000000000000000000000000000000000000000000000000000000000000000000000000000000000000000000000000000000000 !
b1101011 %
b100000000000000000000000000000000000000000000000000000000000000000000000000000000000000000000000000000000000 '
b10000000000000000000000000000000000000000000 5
b101011 6
b101011 *
b1101011 (
b1101011 "
