Scalable PE64/scalable_PE64 (main - 180nm)/Code Files/priority_encoder.v

module pe4 (
    input  wire [3:0] d,
    output wire [1:0] q,
    output wire       v
);
    assign q[1] = d[3] | d[2];
    assign q[0] = d[3] | (d[1] & ~d[2]);
    assign v = |d;
endmodule

module pe16 (
    input  wire [15:0] d,
    output wire [3:0]  q,
    output wire        v
);
    wire [3:0] row_status;
    reg  [3:0] selected_row;
    wire [1:0] row_index;
    wire [1:0] col_index;
    wire       row_valid;

    assign row_status[0] = |d[3:0];
    assign row_status[1] = |d[7:4];
    assign row_status[2] = |d[11:8];
    assign row_status[3] = |d[15:12];

    pe4 row_pe (
        .d(row_status),
        .q(row_index),
        .v(row_valid)
    );

    always @(*) begin
        case (row_index)
            2'b00: selected_row = d[3:0];
            2'b01: selected_row = d[7:4];
            2'b10: selected_row = d[11:8];
            2'b11: selected_row = d[15:12];
            default: selected_row = 4'b0000;
        endcase
    end

    pe4 col_pe (
        .d(selected_row),
        .q(col_index),
        .v()
    );

    assign q = {row_index, col_index};
    assign v = row_valid;
endmodule

module pe64_standard (
    input  wire [63:0] d,
    output wire [5:0]  q,
    output wire        v
);
    wire [15:0] row_status;
    reg  [3:0]  selected_row;
    wire [3:0]  row_index;
    wire [1:0]  col_index;
    wire        row_valid;

    genvar i;
    generate
        for (i = 0; i < 16; i = i + 1) begin : row_logic
            assign row_status[i] = |d[(i*4)+3 : i*4];
        end
    endgenerate

    pe16 row_pe (
        .d(row_status),
        .q(row_index),
        .v(row_valid)
    );

    always @(*) begin
        case (row_index)
            4'h0: selected_row = d[3:0];   4'h1: selected_row = d[7:4];
            4'h2: selected_row = d[11:8];  4'h3: selected_row = d[15:12];
            4'h4: selected_row = d[19:16]; 4'h5: selected_row = d[23:20];
            4'h6: selected_row = d[27:24]; 4'h7: selected_row = d[31:28];
            4'h8: selected_row = d[35:32]; 4'h9: selected_row = d[39:36];
            4'hA: selected_row = d[43:40]; 4'hB: selected_row = d[47:44];
            4'hC: selected_row = d[51:48]; 4'hD: selected_row = d[55:52];
            4'hE: selected_row = d[59:56]; 4'hF: selected_row = d[63:60];
            default: selected_row = 4'b0000;
        endcase
    end

    pe4 col_pe (
        .d(selected_row),
        .q(col_index),
        .v()
    );

    assign q = {row_index, col_index};
    assign v = row_valid;
endmodule

module pe64_lookahead (
    input  wire [63:0] d,
    output wire [5:0]  q,
    output wire        v
);
    wire [15:0] dor;
    wire [3:0]  row_index;
    wire [3:0]  column_data;
    wire [1:0]  col_index;
    wire        row_valid;

    genvar i;
    generate
        for (i = 0; i < 16; i = i + 1) begin : row_or_logic
            assign dor[i] = |d[(i*4)+3 : i*4];
        end
    endgenerate

    pe16 row_encoder (
        .d(dor),
        .q(row_index),
        .v(row_valid)
    );

    reg [3:0] column_data_reg;
    always @(*) begin
        casex(dor)
            16'b1xxxxxxxxxxxxxxx: column_data_reg = d[63:60];
            16'b01xxxxxxxxxxxxxx: column_data_reg = d[59:56];
            16'b001xxxxxxxxxxxxx: column_data_reg = d[55:52];
            16'b0001xxxxxxxxxxxx: column_data_reg = d[51:48];
            16'b00001xxxxxxxxxxx: column_data_reg = d[47:44];
            16'b000001xxxxxxxxxx: column_data_reg = d[43:40];
            16'b0000001xxxxxxxxx: column_data_reg = d[39:36];
            16'b00000001xxxxxxxx: column_data_reg = d[35:32];
            16'b000000001xxxxxxx: column_data_reg = d[31:28];
            16'b0000000001xxxxxx: column_data_reg = d[27:24];
            16'b00000000001xxxxx: column_data_reg = d[23:20];
            16'b000000000001xxxx: column_data_reg = d[19:16];
            16'b0000000000001xxx: column_data_reg = d[15:12];
            16'b00000000000001xx: column_data_reg = d[11:8];
            16'b000000000000001x: column_data_reg = d[7:4];
            16'b0000000000000001: column_data_reg = d[3:0];
            default:              column_data_reg = 4'b0;
        endcase
    end

    assign column_data = column_data_reg;

    pe4 col_encoder (
        .d(column_data),
        .q(col_index),
        .v()
    );

    assign q = {row_index, col_index};
    assign v = row_valid;
endmodule

module pe256_scalable (
    input  wire [255:0] d,
    output wire [7:0]   q,
    output wire         v
);
    wire [3:0] block_status;
    wire [1:0] block_index;
    wire [5:0] internal_index;
    wire       block_valid, internal_valid;

    assign block_status[0] = |d[63:0];
    assign block_status[1] = |d[127:64];
    assign block_status[2] = |d[191:128];
    assign block_status[3] = |d[255:192];

    pe4 block_selector (
        .d(block_status),
        .q(block_index),
        .v(block_valid)
    );

    wire [63:0] selected_block;
    assign selected_block = (block_index == 2'b00) ? d[63:0]     :
                            (block_index == 2'b01) ? d[127:64]   :
                            (block_index == 2'b10) ? d[191:128]  :
                            (block_index == 2'b11) ? d[255:192]  : 64'b0;

    pe64_lookahead internal_pe (
        .d(selected_block),
        .q(internal_index),
        .v(internal_valid)
    );

    assign q = {block_index, internal_index};
    assign v = block_valid;
endmodule

Scalable PE64/scalable_PE64 (main - 90nm)/Code Files/priority_encoder_tb.v
`timescale 1ns / 1ps
`include "priority_encoder.v"

module tb_pe256_scalable_selfchecking();

    reg  [255:0] tb_d;
    wire [7:0]   tb_q;
    wire         tb_v;

    integer error_count;
    reg [7:0] expected_q;
    integer i;

    pe256_scalable dut (
        .d(tb_d),
        .q(tb_q),
        .v(tb_v)
    );

    // CORRECTED FUNCTION FOR VERILOG-2001
    function [7:0] get_expected_q(input [255:0] d);
        integer i;
        begin : find_bit_block // Named block for disable
            get_expected_q = 8'b0; // Default value if no bit is set
            for (i = 255; i >= 0; i = i - 1) begin
                if (d[i] == 1'b1) begin
                    get_expected_q = i; // Assign return value to function name
                    disable find_bit_block; // Exit the loop and function
                end
            end
        end
    endfunction

    initial begin
        $dumpfile("pe256.vcd");
        $dumpvars(0, tb_pe256_scalable_selfchecking);
        error_count = 0;
        
        tb_d = 256'b0;
        #10;
        if (tb_v !== 1'b0) begin
            $display("FAIL: All-zero input, but valid signal is high.");
            error_count = error_count + 1;
        end

        for (i = 0; i < 256; i = i + 1) begin
            tb_d = 0;
            tb_d[i] = 1'b1;
            expected_q = i;
            #10;
            if (tb_q !== expected_q || tb_v !== 1'b1) begin
                $display("FAIL: Input bit %0d | Expected: %0d | Got: %0d", i, expected_q, tb_q);
                error_count = error_count + 1;
            end
        end

        tb_d = 0;
        tb_d[123] = 1'b1;
        tb_d[200] = 1'b1;
        tb_d[5]   = 1'b1;
        expected_q = 200;
        #10;
        if (tb_q !== expected_q) begin
            $display("FAIL: Multi-bit test | Expected: %0d | Got: %0d", expected_q, tb_q);
            error_count = error_count + 1;
        end

        for (i = 0; i < 20; i = i + 1) begin
            tb_d = {$random, $random, $random, $random, $random, $random, $random, $random};
            expected_q = get_expected_q(tb_d);
            #10;
            if (tb_q !== expected_q) begin
                $display("FAIL: Random test | Input: %h | Expected: %0d | Got: %0d", tb_d, expected_q, tb_q);
                error_count = error_count + 1;
            end
        end

        #20;
        if (error_count == 0) begin
            $display("SUCCESS: All tests passed!");
        end else begin
            $display("FAILURE: %0d errors found.", error_count);
        end

        $finish;
    end

endmodule

Scalable PE64/scalable_PE64 (main - 90nm)/Code Files/pe256.vcd
$date
    Oct  8, 2025  13:50:45
$end
$version
    TOOL:	ncsim(64)	15.20-s086
$end
$timescale
    1 ps
$end

$scope module tb_pe256_scalable_selfchecking $end
$var reg      256 !    tb_d [255:0] $end
$var wire      8 "    tb_q [7:0] $end
$var wire      1 #    tb_v  $end
$var integer  32 $    error_count  $end
$var reg       8 %    expected_q [7:0] $end
$var integer  32 &    i  $end

$scope module dut $end
$var wire     256 '    d [255:0] $end
$var wire      8 "    q [7:0] $end
$var wire      1 #    v  $end
$var wire      1 (    block_status [3] $end
$var wire      1 )    block_status [2] $end
$var wire      1 *    block_status [1] $end
$var wire      1 +    block_status [0] $end
$var wire      1 ,    block_index [1] $end
$var wire      1 -    block_index [0] $end
$var wire      6 .    internal_index [5:0] $end
$var wire      1 /    block_valid  $end
$var wire      1 0    internal_valid  $end
$var wire     64 1    selected_block [63:0] $end

$scope module block_selector $end
$var wire      1 (    d [3] $end
$var wire      1 )    d [2] $end
$var wire      1 *    d [1] $end
$var wire      1 +    d [0] $end
$var wire      1 ,    q [1] $end
$var wire      1 -    q [0] $end
$var wire      1 /    v  $end
$upscope $end


$scope module internal_pe $end
$var wire     64 1    d [63:0] $end
$var wire      6 .    q [5:0] $end
$var wire      1 0    v  $end
$var wire      1 2    dor [15] $end
$var wire      1 3    dor [14] $end
$var wire      1 4    dor [13] $end
$var wire      1 5    dor [12] $end
$var wire      1 6    dor [11] $end
$var wire      1 7    dor [10] $end
$var wire      1 8    dor [9] $end
$var wire      1 9    dor [8] $end
$var wire      1 :    dor [7] $end
$var wire      1 ;    dor [6] $end
$var wire      1 <    dor [5] $end
$var wire      1 =    dor [4] $end
$var wire      1 >    dor [3] $end
$var wire      1 ?    dor [2] $end
$var wire      1 @    dor [1] $end
$var wire      1 A    dor [0] $end
$var wire      4 B    row_index [3:0] $end
$var wire      4 C    column_data [3:0] $end
$var wire      1 D    col_index [1] $end
$var wire      1 E    col_index [0] $end
$var wire      1 F    row_valid  $end
$var reg       4 G    column_data_reg [3:0] $end

$scope begin row_or_logic[0] $end
$var parameter 32 H    i [31:0] $end
$upscope $end


$scope begin row_or_logic[1] $end
$var parameter 32 I    i [31:0] $end
$upscope $end


$scope begin row_or_logic[2] $end
$var parameter 32 J    i [31:0] $end
$upscope $end


$scope begin row_or_logic[3] $end
$var parameter 32 K    i [31:0] $end
$upscope $end


$scope begin row_or_logic[4] $end
$var parameter 32 L    i [31:0] $end
$upscope $end


$scope begin row_or_logic[5] $end
$var parameter 32 M    i [31:0] $end
$upscope $end


$scope begin row_or_logic[6] $end
$var parameter 32 N    i [31:0] $end
$upscope $end


$scope begin row_or_logic[7] $end
$var parameter 32 O    i [31:0] $end
$upscope $end


$scope begin row_or_logic[8] $end
$var parameter 32 P    i [31:0] $end
$upscope $end


$scope begin row_or_logic[9] $end
$var parameter 32 Q    i [31:0] $end
$upscope $end


$scope begin row_or_logic[10] $end
$var parameter 32 R    i [31:0] $end
$upscope $end


$scope begin row_or_logic[11] $end
$var parameter 32 S    i [31:0] $end
$upscope $end


$scope begin row_or_logic[12] $end
$var parameter 32 T    i [31:0] $end
$upscope $end


$scope begin row_or_logic[13] $end
$var parameter 32 U    i [31:0] $end
$upscope $end


$scope begin row_or_logic[14] $end
$var parameter 32 V    i [31:0] $end
$upscope $end


$scope begin row_or_logic[15] $end
$var parameter 32 W    i [31:0] $end
$upscope $end


$scope module row_encoder $end
$var wire      1 2    d [15] $end
$var wire      1 3    d [14] $end
$var wire      1 4    d [13] $end
$var wire      1 5    d [12] $end
$var wire      1 6    d [11] $end
$var wire      1 7    d [10] $end
$var wire      1 8    d [9] $end
$var wire      1 9    d [8] $end
$var wire      1 :    d [7] $end
$var wire      1 ;    d [6] $end
$var wire      1 <    d [5] $end
$var wire      1 =    d [4] $end
$var wire      1 >    d [3] $end
$var wire      1 ?    d [2] $end
$var wire      1 @    d [1] $end
$var wire      1 A    d [0] $end
$var wire      4 B    q [3:0] $end
$var wire      1 F    v  $end
$var wire      1 X    row_status [3] $end
$var wire      1 Y    row_status [2] $end
$var wire      1 Z    row_status [1] $end
$var wire      1 [    row_status [0] $end
$var reg       4 \    selected_row [3:0] $end
$var wire      1 ]    row_index [1] $end
$var wire      1 ^    row_index [0] $end
$var wire      1 _    col_index [1] $end
$var wire      1 `    col_index [0] $end
$var wire      1 a    row_valid  $end

$scope module row_pe $end
$var wire      1 X    d [3] $end
$var wire      1 Y    d [2] $end
$var wire      1 Z    d [1] $end
$var wire      1 [    d [0] $end
$var wire      1 ]    q [1] $end
$var wire      1 ^    q [0] $end
$var wire      1 a    v  $end
$upscope $end


$scope module col_pe $end
$var wire      4 b    d [3:0] $end
$var wire      1 _    q [1] $end
$var wire      1 `    q [0] $end
$var wire      1 c    v  $end
$upscope $end

$upscope $end


$scope module col_encoder $end
$var wire      4 C    d [3:0] $end
$var wire      1 D    q [1] $end
$var wire      1 E    q [0] $end
$var wire      1 d    v  $end
$upscope $end

$upscope $end

$upscope $end


$scope function get_expected_q $end
$var reg       8 e    get_expected_q [7:0] $end
$var reg      256 f    d [255:0] $end
$var integer  32 g    i  $end
$upscope $end

$upscope $end

$enddefinitions $end
$dumpvars
b1111 W
b1110 V
b1101 U
b1100 T
b1011 S
b1010 R
b1001 Q
b1000 P
b111 O
b110 N
b101 M
b100 L
b11 K
b10 J
b1 I
b0 H
b0 !
b0 "
0#
b0 $
bx %
bx &
b0 '
0(
0)
0*
0+
0,
0-
b0 .
0/
00
b0 1
02
03
04
05
06
07
08
09
0:
0;
0<
0=
0>
0?
0@
0A
b0 B
b0 C
0D
0E
0F
b0 G
0X
0Y
0Z
0[
b0 \
0]
0^
0_
0`
0a
b0 b
0c
0d
bx e
bx f
bx g
$end
#10000
b0 &
b1 !
b0 %
b1 '
1+
b1 1
1A
1/
1#
b1 G
b1 \
b1 b
b1 C
1[
1a
1d
1c
1F
10
#20000
b1 &
b0 !
b10 !
b1 %
b10 '
b10 1
b10 G
b10 C
1E
b1 .
b1 "
#30000
b10 &
b0 !
b100 !
b10 %
b100 '
b100 1
b100 G
b100 C
1D
0E
b10 .
b10 "
#40000
b11 &
b0 !
b1000 !
b11 %
b1000 '
b1000 1
b1000 G
b1000 C
1E
b11 .
b11 "
#50000
b100 &
b0 !
b10000 !
b100 %
b10000 '
b10000 1
b0 G
b0 C
0A
1@
b1 G
b10 \
b10 b
b1 C
0D
0E
0d
b0 .
1d
1`
b1 B
b0 "
b100 .
b100 "
#60000
b101 &
b0 !
b100000 !
b101 %
b100000 '
b100000 1
b10 G
b10 C
1E
b101 .
b101 "
#70000
b110 &
b0 !
b1000000 !
b110 %
b1000000 '
b1000000 1
b100 G
b100 C
1D
0E
b110 .
b110 "
#80000
b111 &
b0 !
b10000000 !
b111 %
b10000000 '
b10000000 1
b1000 G
b1000 C
1E
b111 .
b111 "
#90000
b1000 &
b0 !
b100000000 !
b1000 %
b100000000 '
b100000000 1
b0 G
b0 C
0@
1?
b1 G
b100 \
b100 b
b1 C
0D
0E
0d
b100 .
1d
1_
0`
b10 B
b100 "
b1000 .
b1000 "
#100000
b1001 &
b0 !
b1000000000 !
b1001 %
b1000000000 '
b1000000000 1
b10 G
b10 C
1E
b1001 .
b1001 "
#110000
b1010 &
b0 !
b10000000000 !
b1010 %
b10000000000 '
b10000000000 1
b100 G
b100 C
1D
0E
b1010 .
b1010 "
#120000
b1011 &
b0 !
b100000000000 !
b1011 %
b100000000000 '
b100000000000 1
b1000 G
b1000 C
1E
b1011 .
b1011 "
#130000
b1100 &
b0 !
b1000000000000 !
b1100 %
b1000000000000 '
b1000000000000 1
b0 G
b0 C
0?
1>
b1 G
b1000 \
b1000 b
b1 C
0D
0E
0d
b1000 .
1d
1`
b11 B
b1000 "
b1100 .
b1100 "
#140000
b1101 &
b0 !
b10000000000000 !
b1101 %
b10000000000000 '
b10000000000000 1
b10 G
b10 C
1E
b1101 .
b1101 "
#150000
b1110 &
b0 !
b100000000000000 !
b1110 %
b100000000000000 '
b100000000000000 1
b100 G
b100 C
1D
0E
b1110 .
b1110 "
#160000
b1111 &
b0 !
b1000000000000000 !
b1111 %
b1000000000000000 '
b1000000000000000 1
b1000 G
b1000 C
1E
b1111 .
b1111 "
#170000
b10000 &
b0 !
b10000000000000000 !
b10000 %
b10000000000000000 '
b10000000000000000 1
b0 G
b0 C
0>
1=
b1 G
b0 \
b0 b
b1 C
1Z
0[
0D
0E
0d
1^
b1 \
b1 b
b111 B
b1100 .
1d
0_
0`
0c
b100 B
b1100 "
b11100 .
1c
b11100 "
b10000 .
b10000 "
#180000
b10001 &
b0 !
b100000000000000000 !
b10001 %
b100000000000000000 '
b100000000000000000 1
b10 G
b10 C
1E
b10001 .
b10001 "
#190000
b10010 &
b0 !
b1000000000000000000 !
b10010 %
b1000000000000000000 '
b1000000000000000000 1
b100 G
b100 C
1D
0E
b10010 .
b10010 "
#200000
b10011 &
b0 !
b10000000000000000000 !
b10011 %
b10000000000000000000 '
b10000000000000000000 1
b1000 G
b1000 C
1E
b10011 .
b10011 "
#210000
b10100 &
b0 !
b100000000000000000000 !
b10100 %
b100000000000000000000 '
b100000000000000000000 1
b0 G
b0 C
0=
1<
b1 G
b10 \
b10 b
b1 C
0D
0E
0d
b10000 .
1d
1`
b101 B
b10000 "
b10100 .
b10100 "
#220000
b10101 &
b0 !
b1000000000000000000000 !
b10101 %
b1000000000000000000000 '
b1000000000000000000000 1
b10 G
b10 C
1E
b10101 .
b10101 "
#230000
b10110 &
b0 !
b10000000000000000000000 !
b10110 %
b10000000000000000000000 '
b10000000000000000000000 1
b100 G
b100 C
1D
0E
b10110 .
b10110 "
#240000
b10111 &
b0 !
b100000000000000000000000 !
b10111 %
b100000000000000000000000 '
b100000000000000000000000 1
b1000 G
b1000 C
1E
b10111 .
b10111 "
#250000
b11000 &
b0 !
b1000000000000000000000000 !
b11000 %
b1000000000000000000000000 '
b1000000000000000000000000 1
b0 G
b0 C
0<
1;
b1 G
b100 \
b100 b
b1 C
0D
0E
0d
b10100 .
1d
1_
0`
b110 B
b10100 "
b11000 .
b11000 "
#260000
b11001 &
b0 !
b10000000000000000000000000 !
b11001 %
b10000000000000000000000000 '
b10000000000000000000000000 1
b10 G
b10 C
1E
b11001 .
b11001 "
#270000
b11010 &
b0 !
b100000000000000000000000000 !
b11010 %
b100000000000000000000000000 '
b100000000000000000000000000 1
b100 G
b100 C
1D
0E
b11010 .
b11010 "
#280000
b11011 &
b0 !
b1000000000000000000000000000 !
b11011 %
b1000000000000000000000000000 '
b1000000000000000000000000000 1
b1000 G
b1000 C
1E
b11011 .
b11011 "
#290000
b11100 &
b0 !
b10000000000000000000000000000 !
b11100 %
b10000000000000000000000000000 '
b10000000000000000000000000000 1
b0 G
b0 C
0;
1:
b1 G
b1000 \
b1000 b
b1 C
0D
0E
0d
b11000 .
1d
1`
b111 B
b11000 "
b11100 .
b11100 "
#300000
b11101 &
b0 !
b100000000000000000000000000000 !
b11101 %
b100000000000000000000000000000 '
b100000000000000000000000000000 1
b10 G
b10 C
1E
b11101 .
b11101 "
#310000
b11110 &
b0 !
b1000000000000000000000000000000 !
b11110 %
b1000000000000000000000000000000 '
b1000000000000000000000000000000 1
b100 G
b100 C
1D
0E
b11110 .
b11110 "
#320000
b11111 &
b0 !
b10000000000000000000000000000000 !
b11111 %
b10000000000000000000000000000000 '
b10000000000000000000000000000000 1
b1000 G
b1000 C
1E
b11111 .
b11111 "
#330000
b100000 &
b0 !
b100000000000000000000000000000000 !
b100000 %
b100000000000000000000000000000000 '
b100000000000000000000000000000000 1
b0 G
b0 C
0:
19
b1 G
b0 \
b0 b
b1 C
1Y
0Z
0D
0E
0d
0^
1]
b1 \
b1 b
b1011 B
b11100 .
1d
0_
0`
0c
b1000 B
b11100 "
b101100 .
1c
b101100 "
b100000 .
b100000 "
#340000
b100001 &
b0 !
b1000000000000000000000000000000000 !
b100001 %
b1000000000000000000000000000000000 '
b1000000000000000000000000000000000 1
b10 G
b10 C
1E
b100001 .
b100001 "
#350000
b100010 &
b0 !
b10000000000000000000000000000000000 !
b100010 %
b10000000000000000000000000000000000 '
b10000000000000000000000000000000000 1
b100 G
b100 C
1D
0E
b100010 .
b100010 "
#360000
b100011 &
b0 !
b100000000000000000000000000000000000 !
b100011 %
b100000000000000000000000000000000000 '
b100000000000000000000000000000000000 1
b1000 G
b1000 C
1E
b100011 .
b100011 "
#370000
b100100 &
b0 !
b1000000000000000000000000000000000000 !
b100100 %
b1000000000000000000000000000000000000 '
b1000000000000000000000000000000000000 1
b0 G
b0 C
09
18
b1 G
b10 \
b10 b
b1 C
0D
0E
0d
b100000 .
1d
1`
b1001 B
b100000 "
b100100 .
b100100 "
#380000
b100101 &
b0 !
b10000000000000000000000000000000000000 !
b100101 %
b10000000000000000000000000000000000000 '
b10000000000000000000000000000000000000 1
b10 G
b10 C
1E
b100101 .
b100101 "
#390000
b100110 &
b0 !
b100000000000000000000000000000000000000 !
b100110 %
b100000000000000000000000000000000000000 '
b100000000000000000000000000000000000000 1
b100 G
b100 C
1D
0E
b100110 .
b100110 "
#400000
b100111 &
b0 !
b1000000000000000000000000000000000000000 !
b100111 %
b1000000000000000000000000000000000000000 '
b1000000000000000000000000000000000000000 1
b1000 G
b1000 C
1E
b100111 .
b100111 "
#410000
b101000 &
b0 !
b10000000000000000000000000000000000000000 !
b101000 %
b10000000000000000000000000000000000000000 '
b10000000000000000000000000000000000000000 1
b0 G
b0 C
08
17
b1 G
b100 \
b100 b
b1 C
0D
0E
0d
b100100 .
1d
1_
0`
b1010 B
b100100 "
b101000 .
b101000 "
#420000
b101001 &
b0 !
b100000000000000000000000000000000000000000 !
b101001 %
b100000000000000000000000000000000000000000 '
b100000000000000000000000000000000000000000 1
b10 G
b10 C
1E
b101001 .
b101001 "
#430000
b101010 &
b0 !
b1000000000000000000000000000000000000000000 !
b101010 %
b1000000000000000000000000000000000000000000 '
b1000000000000000000000000000000000000000000 1
b100 G
b100 C
1D
0E
b101010 .
b101010 "
#440000
b101011 &
b0 !
b10000000000000000000000000000000000000000000 !
b101011 %
b10000000000000000000000000000000000000000000 '
b10000000000000000000000000000000000000000000 1
b1000 G
b1000 C
1E
b101011 .
b101011 "
#450000
b101100 &
b0 !
b100000000000000000000000000000000000000000000 !
b101100 %
b100000000000000000000000000000000000000000000 '
b100000000000000000000000000000000000000000000 1
b0 G
b0 C
07
16
b1 G
b1000 \
b1000 b
b1 C
0D
0E
0d
b101000 .
1d
1`
b1011 B
b101000 "
b101100 .
b101100 "
#460000
b101101 &
b0 !
b1000000000000000000000000000000000000000000000 !
b101101 %
b1000000000000000000000000000000000000000000000 '
b1000000000000000000000000000000000000000000000 1
b10 G
b10 C
1E
b101101 .
b101101 "
#470000
b101110 &
b0 !
b10000000000000000000000000000000000000000000000 !
b101110 %
b10000000000000000000000000000000000000000000000 '
b10000000000000000000000000000000000000000000000 1
b100 G
b100 C
1D
0E
b101110 .
b101110 "
#480000
b101111 &
b0 !
b100000000000000000000000000000000000000000000000 !
b101111 %
b100000000000000000000000000000000000000000000000 '
b100000000000000000000000000000000000000000000000 1
b1000 G
b1000 C
1E
b101111 .
b101111 "
#490000
b110000 &
b0 !
b1000000000000000000000000000000000000000000000000 !
b110000 %
b1000000000000000000000000000000000000000000000000 '
b1000000000000000000000000000000000000000000000000 1
b0 G
b0 C
06
15
b1 G
b0 \
b0 b
b1 C
1X
0Y
0D
0E
0d
1^
b1 \
b1 b
b1111 B
b101100 .
1d
0_
0`
0c
b1100 B
b101100 "
b111100 .
1c
b111100 "
b110000 .
b110000 "
#500000
b110001 &
b0 !
b10000000000000000000000000000000000000000000000000 !
b110001 %
b10000000000000000000000000000000000000000000000000 '
b10000000000000000000000000000000000000000000000000 1
b10 G
b10 C
1E
b110001 .
b110001 "
#510000
b110010 &
b0 !
b100000000000000000000000000000000000000000000000000 !
b110010 %
b100000000000000000000000000000000000000000000000000 '
b100000000000000000000000000000000000000000000000000 1
b100 G
b100 C
1D
0E
b110010 .
b110010 "
#520000
b110011 &
b0 !
b1000000000000000000000000000000000000000000000000000 !
b110011 %
b1000000000000000000000000000000000000000000000000000 '
b1000000000000000000000000000000000000000000000000000 1
b1000 G
b1000 C
1E
b110011 .
b110011 "
#530000
b110100 &
b0 !
b10000000000000000000000000000000000000000000000000000 !
b110100 %
b10000000000000000000000000000000000000000000000000000 '
b10000000000000000000000000000000000000000000000000000 1
b0 G
b0 C
05
14
b1 G
b10 \
b10 b
b1 C
0D
0E
0d
b110000 .
1d
1`
b1101 B
b110000 "
b110100 .
b110100 "
#540000
b110101 &
b0 !
b100000000000000000000000000000000000000000000000000000 !
b110101 %
b100000000000000000000000000000000000000000000000000000 '
b100000000000000000000000000000000000000000000000000000 1
b10 G
b10 C
1E
b110101 .
b110101 "
#550000
b110110 &
b0 !
b1000000000000000000000000000000000000000000000000000000 !
b110110 %
b1000000000000000000000000000000000000000000000000000000 '
b1000000000000000000000000000000000000000000000000000000 1
b100 G
b100 C
1D
0E
b110110 .
b110110 "
#560000
b110111 &
b0 !
b10000000000000000000000000000000000000000000000000000000 !
b110111 %
b10000000000000000000000000000000000000000000000000000000 '
b10000000000000000000000000000000000000000000000000000000 1
b1000 G
b1000 C
1E
b110111 .
b110111 "
#570000
b111000 &
b0 !
b100000000000000000000000000000000000000000000000000000000 !
b111000 %
b100000000000000000000000000000000000000000000000000000000 '
b100000000000000000000000000000000000000000000000000000000 1
b0 G
b0 C
04
13
b1 G
b100 \
b100 b
b1 C
0D
0E
0d
b110100 .
1d
1_
0`
b1110 B
b110100 "
b111000 .
b111000 "
#580000
b111001 &
b0 !
b1000000000000000000000000000000000000000000000000000000000 !
b111001 %
b1000000000000000000000000000000000000000000000000000000000 '
b1000000000000000000000000000000000000000000000000000000000 1
b10 G
b10 C
1E
b111001 .
b111001 "
#590000
b111010 &
b0 !
b10000000000000000000000000000000000000000000000000000000000 !
b111010 %
b10000000000000000000000000000000000000000000000000000000000 '
b10000000000000000000000000000000000000000000000000000000000 1
b100 G
b100 C
1D
0E
b111010 .
b111010 "
#600000
b111011 &
b0 !
b100000000000000000000000000000000000000000000000000000000000 !
b111011 %
b100000000000000000000000000000000000000000000000000000000000 '
b100000000000000000000000000000000000000000000000000000000000 1
b1000 G
b1000 C
1E
b111011 .
b111011 "
#610000
b111100 &
b0 !
b1000000000000000000000000000000000000000000000000000000000000 !
b111100 %
b1000000000000000000000000000000000000000000000000000000000000 '
b1000000000000000000000000000000000000000000000000000000000000 1
b0 G
b0 C
03
12
b1 G
b1000 \
b1000 b
b1 C
0D
0E
0d
b111000 .
1d
1`
b1111 B
b111000 "
b111100 .
b111100 "
#620000
b111101 &
b0 !
b10000000000000000000000000000000000000000000000000000000000000 !
b111101 %
b10000000000000000000000000000000000000000000000000000000000000 '
b10000000000000000000000000000000000000000000000000000000000000 1
b10 G
b10 C
1E
b111101 .
b111101 "
#630000
b111110 &
b0 !
b100000000000000000000000000000000000000000000000000000000000000 !
b111110 %
b100000000000000000000000000000000000000000000000000000000000000 '
b100000000000000000000000000000000000000000000000000000000000000 1
b100 G
b100 C
1D
0E
b111110 .
b111110 "
#640000
b111111 &
b0 !
b1000000000000000000000000000000000000000000000000000000000000000 !
b111111 %
b1000000000000000000000000000000000000000000000000000000000000000 '
b1000000000000000000000000000000000000000000000000000000000000000 1
b1000 G
b1000 C
1E
b111111 .
b111111 "
#650000
b1000000 &
b0 !
b10000000000000000000000000000000000000000000000000000000000000000 !
b1000000 %
b10000000000000000000000000000000000000000000000000000000000000000 '
0+
1*
b0 1
1-
b0 G
b0 C
b1 1
b1111111 "
02
b0 \
b0 b
0X
1A
0D
0E
0d
0^
0]
b1 G
b1 \
b1 b
b1 C
b11 B
b111100 .
1[
0a
0_
0`
0c
0F
00
b0 B
1a
b1111100 "
b1100 .
1d
1c
1F
10
b1001100 "
b0 .
b1000000 "
#660000
b1000001 &
b0 !
b100000000000000000000000000000000000000000000000000000000000000000 !
b1000001 %
b100000000000000000000000000000000000000000000000000000000000000000 '
b10 1
b10 G
b10 C
1E
b1 .
b1000001 "
#670000
b1000010 &
b0 !
b1000000000000000000000000000000000000000000000000000000000000000000 !
b1000010 %
b1000000000000000000000000000000000000000000000000000000000000000000 '
b100 1
b100 G
b100 C
1D
0E
b10 .
b1000010 "
#680000
b1000011 &
b0 !
b10000000000000000000000000000000000000000000000000000000000000000000 !
b1000011 %
b10000000000000000000000000000000000000000000000000000000000000000000 '
b1000 1
b1000 G
b1000 C
1E
b11 .
b1000011 "
#690000
b1000100 &
b0 !
b100000000000000000000000000000000000000000000000000000000000000000000 !
b1000100 %
b100000000000000000000000000000000000000000000000000000000000000000000 '
b10000 1
b0 G
b0 C
0A
1@
b1 G
b10 \
b10 b
b1 C
0D
0E
0d
b0 .
1d
1`
b1 B
b1000000 "
b100 .
b1000100 "
#700000
b1000101 &
b0 !
b1000000000000000000000000000000000000000000000000000000000000000000000 !
b1000101 %
b1000000000000000000000000000000000000000000000000000000000000000000000 '
b100000 1
b10 G
b10 C
1E
b101 .
b1000101 "
#710000
b1000110 &
b0 !
b10000000000000000000000000000000000000000000000000000000000000000000000 !
b1000110 %
b10000000000000000000000000000000000000000000000000000000000000000000000 '
b1000000 1
b100 G
b100 C
1D
0E
b110 .
b1000110 "
#720000
b1000111 &
b0 !
b100000000000000000000000000000000000000000000000000000000000000000000000 !
b1000111 %
b100000000000000000000000000000000000000000000000000000000000000000000000 '
b10000000 1
b1000 G
b1000 C
1E
b111 .
b1000111 "
#730000
b1001000 &
b0 !
b1000000000000000000000000000000000000000000000000000000000000000000000000 !
b1001000 %
b1000000000000000000000000000000000000000000000000000000000000000000000000 '
b100000000 1
b0 G
b0 C
0@
1?
b1 G
b100 \
b100 b
b1 C
0D
0E
0d
b100 .
1d
1_
0`
b10 B
b1000100 "
b1000 .
b1001000 "
#740000
b1001001 &
b0 !
b10000000000000000000000000000000000000000000000000000000000000000000000000 !
b1001001 %
b10000000000000000000000000000000000000000000000000000000000000000000000000 '
b1000000000 1
b10 G
b10 C
1E
b1001 .
b1001001 "
#750000
b1001010 &
b0 !
b100000000000000000000000000000000000000000000000000000000000000000000000000 !
b1001010 %
b100000000000000000000000000000000000000000000000000000000000000000000000000 '
b10000000000 1
b100 G
b100 C
1D
0E
b1010 .
b1001010 "
#760000
b1001011 &
b0 !
b1000000000000000000000000000000000000000000000000000000000000000000000000000 !
b1001011 %
b1000000000000000000000000000000000000000000000000000000000000000000000000000 '
b100000000000 1
b1000 G
b1000 C
1E
b1011 .
b1001011 "
